<?xml version='1.0' encoding='utf-8' ?>
<!DOCTYPE LIGO_LW [
<!ELEMENT LIGO_LW ((LIGO_LW|Comment|Param|Table|Array|Stream|IGWDFrame|AdcData|AdcInterval|Time|Detector)*)>
<!ATTLIST LIGO_LW
         Name CDATA #IMPLIED
         Type CDATA #IMPLIED>

<!ELEMENT Comment (#PCDATA)>

<!ELEMENT Param (#PCDATA|Comment)*>
<!ATTLIST Param 
         Name CDATA #IMPLIED
         Type CDATA #IMPLIED
         Start CDATA #IMPLIED
         Scale CDATA #IMPLIED
         Unit CDATA #IMPLIED
         DataUnit CDATA #IMPLIED>

<!ELEMENT Table (Comment?,Column*,Stream?)>
<!ATTLIST Table 
         Name CDATA #IMPLIED
         Type CDATA #IMPLIED>

<!ELEMENT Column EMPTY>
<!ATTLIST Column
         Name CDATA #IMPLIED
         Type CDATA #IMPLIED
         Unit CDATA #IMPLIED>

<!ELEMENT Array (Dim*,Stream?)>
<!ATTLIST Array 
         Name CDATA #IMPLIED
         Type CDATA #IMPLIED
         Unit CDATA #IMPLIED>

<!ELEMENT Dim (#PCDATA)>
<!ATTLIST Dim 
         Name  CDATA #IMPLIED
         Unit CDATA #IMPLIED
         Start CDATA #IMPLIED
         Scale CDATA #IMPLIED>

<!ELEMENT Stream (#PCDATA)>
<!ATTLIST Stream 
         Name      CDATA #IMPLIED
         Type      (Remote|Local) "Local"
         Delimiter CDATA ","
         Encoding  CDATA #IMPLIED
         Content   CDATA #IMPLIED>

<!ELEMENT IGWDFrame ((Comment|Param|Time|Detector|AdcData|LIGO_LW|Stream?|Array|IGWDFrame)*)>
<!ATTLIST IGWDFrame 
         Name CDATA #IMPLIED>

<!ELEMENT Detector ((Comment|Param|LIGO_LW)*)>
<!ATTLIST Detector 
         Name CDATA #IMPLIED>

<!ELEMENT AdcData ((AdcData|Comment|Param|Time|LIGO_LW|Array)*)>
<!ATTLIST AdcData 
         Name CDATA #IMPLIED>

<!ELEMENT AdcInterval ((AdcData|Comment|Time)*)>
<!ATTLIST AdcInterval 
         Name CDATA #IMPLIED
         StartTime CDATA #IMPLIED
         DeltaT CDATA #IMPLIED>

<!ELEMENT Time (#PCDATA)>
<!ATTLIST Time 
         Name CDATA #IMPLIED
         Type (GPS|Unix|ISO-8601) "ISO-8601">
]>

<LIGO_LW>
   <Comment>metadata</Comment>
   <Table Name="processgroup:process:table">
      <Column Name="processgroup:process:program" Type="lstring"/>
      <Column Name="processgroup:process:version" Type="lstring"/>
      <Column Name="processgroup:process:cvs_repository" Type="lstring"/>
      <Column Name="processgroup:process:cvs_entry_time" Type="int_4s"/>
      <Column Name="processgroup:process:comment" Type="lstring"/>
      <Column Name="processgroup:process:is_online" Type="int_4s"/>
      <Column Name="processgroup:process:node" Type="lstring"/>
      <Column Name="processgroup:process:username" Type="lstring"/>
      <Column Name="processgroup:process:unix_procid" Type="int_4s"/>
      <Column Name="processgroup:process:start_time" Type="int_4s"/>
      <Column Name="processgroup:process:end_time" Type="int_4s"/>
      <Column Name="processgroup:process:jobid" Type="int_4s"/>
      <Column Name="processgroup:process:domain" Type="lstring"/>
      <Column Name="processgroup:process:ifos" Type="lstring"/>
      <Column Name="processgroup:process:process_id" Type="ilwd:char"/>
      <Stream Name="processgroup:process:table" Type="Local" Delimiter=",">
         "sire","1.15","/usr/local/cvs/lscsoft/lalapps/src/inspiral/sire.c\,v",769623277," ",0,"ldas-grid","dbrown",25038,776378542,776378542,0,"lalapps","","process:process_id:0"
      </Stream>
   </Table>
   <Table Name="process_paramsgroup:process_params:table">
      <Column Name="process_paramsgroup:process_params:program" Type="lstring"/>
      <Column Name="process_paramsgroup:process_params:process_id" Type="ilwd:char"/>
      <Column Name="process_paramsgroup:process_params:param" Type="lstring"/>
      <Column Name="process_paramsgroup:process_params:type" Type="lstring"/>
      <Column Name="process_paramsgroup:process_params:value" Type="lstring"/>
      <Stream Name="process_paramsgroup:process_params:table" Type="Local" Delimiter=",">
         "sire","process:process_id:0","--playground-only","string"," ",
         "sire","process:process_id:0","--input","string","h1-inca_l1h1.files",
         "sire","process:process_id:0","--output","string","h1-inca_l1h1_inj_clust.xml",
         "sire","process:process_id:0","--debug-level","string","33",
         "sire","process:process_id:0","--injection-coincidence","int","5",
         "sire","process:process_id:0","--cluster-time","int","16",
         "sire","process:process_id:0","--cluster-algorithm","string","snr",
         "sire","process:process_id:0","--injection-file","string","HL-INJECTIONS_2501-729273613-5094000.xml"
      </Stream>
   </Table>
   <Table Name="sim_inspiralgroup:sim_inspiral:table">
      <Column Name="sim_inspiralgroup:sim_inspiral:process_id" Type="ilwd:char"/>
      <Column Name="sim_inspiralgroup:sim_inspiral:waveform" Type="lstring"/>
      <Column Name="sim_inspiralgroup:sim_inspiral:geocent_end_time" Type="int_4s"/>
      <Column Name="sim_inspiralgroup:sim_inspiral:geocent_end_time_ns" Type="int_4s"/>
      <Column Name="sim_inspiralgroup:sim_inspiral:h_end_time" Type="int_4s"/>
      <Column Name="sim_inspiralgroup:sim_inspiral:h_end_time_ns" Type="int_4s"/>
      <Column Name="sim_inspiralgroup:sim_inspiral:l_end_time" Type="int_4s"/>
      <Column Name="sim_inspiralgroup:sim_inspiral:l_end_time_ns" Type="int_4s"/>
      <Column Name="sim_inspiralgroup:sim_inspiral:end_time_gmst" Type="real_8"/>
      <Column Name="sim_inspiralgroup:sim_inspiral:source" Type="lstring"/>
      <Column Name="sim_inspiralgroup:sim_inspiral:mass1" Type="real_4"/>
      <Column Name="sim_inspiralgroup:sim_inspiral:mass2" Type="real_4"/>
      <Column Name="sim_inspiralgroup:sim_inspiral:eta" Type="real_4"/>
      <Column Name="sim_inspiralgroup:sim_inspiral:distance" Type="real_4"/>
      <Column Name="sim_inspiralgroup:sim_inspiral:longitude" Type="real_4"/>
      <Column Name="sim_inspiralgroup:sim_inspiral:latitude" Type="real_4"/>
      <Column Name="sim_inspiralgroup:sim_inspiral:inclination" Type="real_4"/>
      <Column Name="sim_inspiralgroup:sim_inspiral:coa_phase" Type="real_4"/>
      <Column Name="sim_inspiralgroup:sim_inspiral:polarization" Type="real_4"/>
      <Column Name="sim_inspiralgroup:sim_inspiral:eff_dist_h" Type="real_4"/>
      <Column Name="sim_inspiralgroup:sim_inspiral:eff_dist_l" Type="real_4"/>
      <Column Name="sim_inspiralgroup:sim_inspiral:simulation_id" Type="ilwd:char"/>
      <Stream Name="sim_inspiralgroup:sim_inspiral:table" Type="Local" Delimiter=",">
         "process:process_id:0","GeneratePPNtwoPN",729649999,895041466,729649999,878276775,729649999,881542876,1.0455695013374918e+01,"MW",6.577500e-01,5.385053e-01,2.475159e-01,2.517708e-02,2.416225e-01,2.439489e-01,1.515114e+00,5.332174e+00,2.489944e-01,1.043676e-01,2.647804e-01,"sim_inspiral:simulation_id:0",
         "process:process_id:0","GeneratePPNtwoPN",729675331,288252354,729675331,301363231,729675331,306124725,1.7511458418104382e+01,"MW",8.800179e-01,1.689960e-01,1.351467e-01,2.403058e-02,5.324497e-01,-5.749209e-01,1.442416e+00,3.200328e+00,1.142035e+00,8.031876e-02,7.343324e-02,"sim_inspiral:simulation_id:0",
         "process:process_id:0","GeneratePPNtwoPN",729789943,208117962,729789943,223849967,729789943,226843709,1.4352686756807898e+00,"MW",9.725392e-01,6.495712e-01,2.400895e-01,2.886202e-02,2.489823e+00,-7.480308e-01,1.576139e+00,1.936112e-01,3.333076e+00,9.931732e-02,7.202832e-02,"sim_inspiral:simulation_id:0",
         "process:process_id:0","GeneratePPNtwoPN",729802794,480596066,729802794,499189304,729802794,501124585,5.0148403695184323e+00,"MW",5.092868e-01,2.308075e-01,2.146042e-01,3.461510e-02,3.074653e+00,-7.354734e-01,1.249315e+00,1.814842e+00,1.276587e+00,9.026308e-02,8.794819e-02,"sim_inspiral:simulation_id:0",
         "process:process_id:0","GeneratePPNtwoPN",730018984,729349494,730018984,745434072,730018984,737842692,1.7232106491935749e+01,"MW",4.376889e-01,2.126980e-01,2.200824e-01,3.523146e-02,4.660701e+00,-5.954074e-01,1.494170e+00,6.250328e+00,1.020213e+00,1.014976e-01,1.816550e-01,"sim_inspiral:simulation_id:0",
         "process:process_id:0","GeneratePPNtwoPN",730273978,72604418,730273978,93668744,730273978,90458698,1.6257520929587383e+01,"MW",7.890685e-01,9.747810e-01,2.472286e-01,3.834246e-02,5.146518e+00,-7.585942e-01,6.906137e-01,5.368052e+00,6.166425e+00,5.011413e-02,5.909329e-02,"sim_inspiral:simulation_id:0",
         "process:process_id:0","GeneratePPNtwoPN",730458852,254732132,730458852,269256198,730458852,267735377,1.9752062823192940e+01,"MW",8.888917e-01,7.507872e-01,2.482264e-01,3.133814e-02,1.517427e+00,-1.243343e+00,2.803714e+00,4.342643e+00,5.080681e+00,4.724767e-02,5.380851e-02,"sim_inspiral:simulation_id:0",
         "process:process_id:0","GeneratePPNtwoPN",730547646,151363581,730547646,145467410,730547646,145085440,2.0484564570792848e+01,"MW",3.568069e-01,8.825586e-01,2.050114e-01,3.797604e-02,2.922466e+00,-4.409036e-01,1.693447e+00,2.096215e+00,3.837253e+00,2.359338e-01,2.457602e-01,"sim_inspiral:simulation_id:0",
         "process:process_id:0","GeneratePPNtwoPN",730700689,748757362,730700689,761816543,730700689,755959859,1.5113069253994359e+01,"MW",3.301483e-01,1.583501e-01,2.190792e-01,2.718600e-02,4.241192e+00,-1.777826e-01,2.641296e+00,3.111463e+00,2.646515e+00,4.487035e-02,6.258555e-02,"sim_inspiral:simulation_id:0",
         "process:process_id:0","GeneratePPNtwoPN",730713466,649033308,730713466,670259326,730713466,668071419,1.8671925441713796e+01,"MW",5.087330e-01,7.379084e-01,2.415512e-01,2.309179e-02,5.947411e+00,-7.734159e-01,1.449170e+00,4.232379e+00,2.673836e+00,7.440878e-02,8.447826e-02,"sim_inspiral:simulation_id:0",
         "process:process_id:0","GeneratePPNtwoPN",730720152,958276749,730720152,968942028,730720152,961923446,2.0534318709990217e+01,"MW",4.802689e-01,7.799380e-01,2.358636e-01,4.705790e-02,5.473023e+00,-1.536133e-01,1.641152e+00,4.142339e+00,5.971665e+00,1.673236e-01,5.865052e-01,"sim_inspiral:simulation_id:0",
         "process:process_id:0","GeneratePPNtwoPN",731006452,41920900,731006452,50056256,731006452,55207914,4.2795811016071177e+00,"MW",8.620393e-01,3.291458e-01,1.999664e-01,1.675622e-02,3.734234e+00,-5.448645e-01,1.724132e+00,3.324203e+00,5.348420e+00,8.005367e-02,1.240704e-01,"sim_inspiral:simulation_id:0",
         "process:process_id:0","GeneratePPNtwoPN",731165965,941193581,731165965,936632728,731165965,928178168,7.1031271787567274e-01,"MW",6.697874e-01,8.914967e-01,2.449587e-01,1.545266e-02,5.201190e+00,-3.290332e-01,1.624771e+00,1.875113e+00,1.172614e+00,6.213346e-02,4.623019e-02,"sim_inspiral:simulation_id:0",
         "process:process_id:0","GeneratePPNtwoPN",731171983,56865215,731171983,64133166,731171983,58835814,2.3863099458151393e+00,"MW",7.790507e-01,3.505012e-01,2.140144e-01,4.977843e-02,4.969080e+00,-1.109176e+00,4.305857e-01,5.623569e+00,6.104270e+00,1.383172e-01,1.760812e-01,"sim_inspiral:simulation_id:0",
         "process:process_id:0","GeneratePPNtwoPN",731274171,913521767,731274171,930615085,731274171,928106645,6.8498211936487090e+00,"MW",4.729574e-01,1.568614e-01,1.870281e-01,1.025029e-02,3.763470e+00,-1.320115e+00,2.103880e+00,2.203835e+00,5.500071e+00,2.392415e-02,2.837662e-02,"sim_inspiral:simulation_id:0",
         "process:process_id:0","GeneratePPNtwoPN",731306231,780713081,731306231,775807452,731306231,767725139,1.5779722358671327e+01,"MW",1.894829e-01,4.070005e-01,2.167546e-01,2.510173e-02,2.778388e+00,-3.554202e-01,2.713456e+00,2.819394e-01,4.580516e+00,5.273549e-02,4.010176e-02,"sim_inspiral:simulation_id:0",
         "process:process_id:0","GeneratePPNtwoPN",731312036,736535013,731312036,756540885,731312036,756493511,1.7396624926072029e+01,"MW",4.833155e-01,1.816541e-01,1.985511e-01,1.242850e-02,5.715121e+00,-4.749703e-01,1.813973e+00,3.111765e+00,1.280759e+00,5.288968e-02,5.486893e-02,"sim_inspiral:simulation_id:0",
         "process:process_id:0","GeneratePPNtwoPN",731598864,860940456,731598864,863818170,731598864,872518864,1.2892454313031501e+00,"MW",2.436119e-01,4.727659e-01,2.244194e-01,2.595034e-02,2.812453e+00,-4.146034e-02,3.928701e-01,6.095930e+00,6.777498e-01,1.834524e-01,5.076663e-02,"sim_inspiral:simulation_id:0",
         "process:process_id:0","GeneratePPNtwoPN",731605059,240754873,731605059,243056114,731605059,252477683,3.0146175005990599e+00,"MW",6.550392e-01,9.368386e-01,2.421657e-01,4.890649e-03,3.030793e+00,2.048396e-01,1.444159e+00,8.762115e-01,1.228949e+00,1.205753e-01,3.455445e-02,"sim_inspiral:simulation_id:0",
         "process:process_id:0","GeneratePPNtwoPN",731669088,555307865,731669088,558905483,731669088,557678026,2.0849234456097086e+01,"MW",9.410376e-01,2.320999e-01,1.587026e-01,5.676939e-03,2.812780e+00,-8.639870e-01,1.059207e+00,4.337973e+00,2.544411e+00,4.408735e-02,6.149947e-02,"sim_inspiral:simulation_id:0",
         "process:process_id:0","GeneratePPNtwoPN",731675455,983105183,731675455,973112768,731675455,982045234,2.2622807029605738e+01,"MW",8.383393e-01,6.889768e-01,2.476091e-01,3.676086e-02,2.607310e+00,3.608015e-01,2.470331e+00,3.045174e+00,3.888722e+00,9.657354e-02,4.589658e-01,"sim_inspiral:simulation_id:0",
         "process:process_id:0","GeneratePPNtwoPN",731700744,461097002,731700744,457755340,731700744,451874731,5.6666168968420889e+00,"MW",6.898051e-01,4.475641e-01,2.386595e-01,3.744524e-02,5.993337e+00,-5.772035e-01,2.867776e+00,4.875159e+00,1.680334e+00,9.861739e-02,7.944383e-02,"sim_inspiral:simulation_id:0",
         "process:process_id:0","GeneratePPNtwoPN",731719791,592665792,731719791,578069491,731719791,579298662,1.0971972710643378e+01,"MW",7.004878e-01,7.701481e-01,2.494391e-01,1.723855e-02,2.318127e+00,1.215475e+00,1.761885e+00,4.744831e+00,4.992885e+00,7.000300e-02,6.068086e-02,"sim_inspiral:simulation_id:0",
         "process:process_id:0","GeneratePPNtwoPN",731732742,156703949,731732742,158198556,731732742,151610102,1.4579200895180305e+01,"MW",2.212167e-01,6.934521e-01,1.833609e-01,3.176169e-02,3.649928e+00,2.213135e-01,2.315427e+00,6.098165e+00,2.085124e+00,9.937244e-02,8.760347e-02,"sim_inspiral:simulation_id:0",
         "process:process_id:0","GeneratePPNtwoPN",731828527,666743279,731828527,675537048,731828527,666651843,1.7259134814627469e+01,"MW",1.881768e-01,7.135373e-01,1.651373e-01,4.529897e-02,4.323721e+00,-2.899407e-01,9.982399e-01,2.709835e+00,4.464365e+00,1.594776e-01,6.236982e-01,"sim_inspiral:simulation_id:0",
         "process:process_id:0","GeneratePPNtwoPN",731834363,788371041,731834363,806185733,731834363,799722349,1.8884718249431916e+01,"MW",2.802283e-01,5.792594e-01,2.197383e-01,4.705654e-03,5.133732e+00,-1.176365e+00,1.515586e+00,5.849710e+00,3.673582e+00,6.652908e-02,4.322171e-02,"sim_inspiral:simulation_id:0",
         "process:process_id:0","GeneratePPNtwoPN",731891938,808103085,731891938,789509511,731891938,793259800,1.0921566855373483e+01,"MW",5.102497e-01,9.562385e-01,2.268777e-01,3.436113e-02,9.159310e-01,1.308139e+00,1.712630e+00,1.158369e+00,5.063927e-02,1.492854e-01,2.485605e-01,"sim_inspiral:simulation_id:0",
         "process:process_id:0","GeneratePPNtwoPN",731898119,330559552,731898119,340308470,731898119,334064989,1.2643079102817509e+01,"MW",2.708845e-01,4.875369e-01,2.295993e-01,4.038472e-02,1.730309e+00,-1.205971e+00,2.281036e+00,1.176929e-01,2.709570e+00,1.123758e-01,1.408152e-01,"sim_inspiral:simulation_id:0",
         "process:process_id:0","GeneratePPNtwoPN",731910818,789542496,731910818,803350926,731910818,809173837,1.6180364932517211e+01,"MW",8.368097e-01,4.487777e-01,2.272243e-01,3.921522e-02,6.006929e+00,-1.905789e-01,1.349172e+00,2.925792e+00,2.539880e+00,2.418695e-01,1.886322e-01,"sim_inspiral:simulation_id:0",
         "process:process_id:0","GeneratePPNtwoPN",731917447,722942114,731917447,727986352,731917447,718554594,1.8026776822859215e+01,"MW",8.180371e-01,5.732901e-01,2.422640e-01,2.029600e-02,4.308303e+00,-2.360231e-01,1.139670e+00,5.935441e+00,6.279847e+00,1.430512e-01,1.613671e-01,"sim_inspiral:simulation_id:0",
         "process:process_id:0","GeneratePPNtwoPN",731936624,52415371,731936624,71850938,731936624,69989756,2.3368119198655087e+01,"MW",3.954985e-01,3.081568e-01,2.461482e-01,3.334956e-02,7.308515e-01,-4.133134e-01,2.724441e+00,1.352881e+00,4.633507e+00,3.989463e-02,4.353393e-02,"sim_inspiral:simulation_id:0",
         "process:process_id:0","GeneratePPNtwoPN",731949076,29989600,731949076,17956937,731949076,26514799,2.8364719617780714e+00,"MW",3.318452e-01,6.657843e-01,2.219885e-01,3.124059e-02,3.232359e+00,1.021882e+00,1.420092e+00,5.368097e+00,5.528719e+00,1.000299e-01,1.226165e-01,"sim_inspiral:simulation_id:0",
         "process:process_id:0","GeneratePPNtwoPN",731994118,179932117,731994118,175930115,731994118,168685880,1.5382436200454832e+01,"MW",4.971430e-01,6.096652e-01,2.474161e-01,2.634022e-02,2.490127e+00,-4.818025e-01,2.432060e+00,4.226868e+00,1.327089e+00,6.723426e-02,5.452478e-02,"sim_inspiral:simulation_id:0",
         "process:process_id:0","GeneratePPNtwoPN",732350508,798531771,732350508,789201525,732350508,783947366,1.8650876146658426e+01,"MW",3.583458e-01,6.172234e-01,2.323959e-01,3.222947e-02,4.256081e+00,5.412281e-01,1.725673e+00,5.364909e+00,2.622170e+00,2.395743e-01,2.692405e-01,"sim_inspiral:simulation_id:0",
         "process:process_id:0","GeneratePPNtwoPN",732497033,871419907,732497033,883694647,732497033,874472493,1.1463722057880627e+01,"MW",6.735089e-01,4.395210e-01,2.389513e-01,2.823552e-02,2.765264e+00,-6.285987e-01,1.590759e+00,1.258162e+00,4.766803e+00,9.659910e-02,2.719707e-01,"sim_inspiral:simulation_id:0",
         "process:process_id:0","GeneratePPNtwoPN",732548139,442806721,732548139,454899933,732548139,460391768,1.6985814423776335e+00,"MW",5.113904e-01,7.793380e-01,2.392262e-01,3.324835e-02,2.687421e+00,-4.898814e-01,1.192062e+00,1.776653e+00,1.380794e+00,9.857623e-02,7.147890e-02,"sim_inspiral:simulation_id:0",
         "process:process_id:0","GeneratePPNtwoPN",732586023,218525678,732586023,220749932,732586023,213982456,1.2250664239968691e+01,"MW",4.094558e-01,4.113834e-01,2.499986e-01,3.331335e-02,3.050633e+00,1.845242e-01,8.250601e-01,2.907156e+00,5.436900e+00,1.023553e-01,9.697515e-02,"sim_inspiral:simulation_id:0",
         "process:process_id:0","GeneratePPNtwoPN",733076652,728506804,733076652,708190161,733076652,709404915,4.9097778723761438e+00,"MW",8.350869e-01,3.284677e-01,2.026053e-01,2.805236e-02,5.459342e+00,5.124117e-01,2.328579e+00,5.773939e+00,5.521276e+00,4.001926e-02,4.264764e-02,"sim_inspiral:simulation_id:0",
         "process:process_id:0","GeneratePPNtwoPN",733089736,870818615,733089736,872240019,733089736,880914661,8.5542127456764376e+00,"MW",7.021315e-01,1.691394e-01,1.564433e-01,1.861301e-02,4.810136e+00,-3.751182e-02,1.675210e+00,2.466668e+00,4.363593e+00,2.705808e-01,8.727107e-02,"sim_inspiral:simulation_id:0",
         "process:process_id:0","GeneratePPNtwoPN",733376021,238996863,733376021,249198805,733376021,247341907,1.6295376303866504e+01,"MW",8.046287e-01,7.694927e-01,2.498754e-01,4.390536e-02,1.313835e+00,-1.154775e+00,1.404199e+00,1.980661e+00,4.441433e+00,2.225635e-01,4.640451e-01,"sim_inspiral:simulation_id:0",
         "process:process_id:0","GeneratePPNtwoPN",733452386,578676283,733452386,590494908,733452386,586164433,1.3566048820738992e+01,"MW",2.978479e-01,7.922409e-01,1.985766e-01,2.723441e-02,1.233559e+00,-1.348505e+00,1.209695e+00,6.156151e+00,5.616656e+00,8.608735e-02,1.120067e-01,"sim_inspiral:simulation_id:0",
         "process:process_id:0","GeneratePPNtwoPN",733465184,41334271,733465184,20882748,733465184,21486530,1.7130632422053150e+01,"MW",4.395183e-01,4.992130e-01,2.489890e-01,4.041504e-02,2.474045e+00,5.403630e-01,1.455385e+00,1.253417e+00,4.279758e-01,1.727595e-01,2.139389e-01,"sim_inspiral:simulation_id:0",
         "process:process_id:0","GeneratePPNtwoPN",733548028,79201460,733548028,77802231,733548028,69034160,1.6205870572514833e+01,"MW",5.099790e-01,5.229717e-01,2.499605e-01,5.045475e-02,2.999624e+00,-4.909152e-01,2.216958e+00,4.040766e+00,4.258115e+00,1.503207e-01,1.219337e-01,"sim_inspiral:simulation_id:0",
         "process:process_id:0","GeneratePPNtwoPN",733611869,432439089,733611869,445823456,733611869,450051800,9.9881330769550463e+00,"MW",9.911536e-01,7.357858e-01,2.445334e-01,3.568043e-03,3.987264e+00,3.698790e-02,1.856784e+00,2.608065e+00,1.699076e+00,1.154361e-02,8.595226e-03,"sim_inspiral:simulation_id:0",
         "process:process_id:0","GeneratePPNtwoPN",733637465,627611160,733637465,624689710,733637465,615507717,1.7117653978173102e+01,"MW",9.676785e-01,9.891201e-01,2.499700e-01,1.331837e-02,3.673003e+00,-8.698865e-02,1.224430e+00,2.932450e+00,2.861200e+00,1.338672e-01,4.297918e-02,"sim_inspiral:simulation_id:0",
         "process:process_id:0","GeneratePPNtwoPN",733701259,215963364,733701259,233610143,733701259,236901634,1.0886612162118157e+01,"MW",6.842161e-01,4.177767e-01,2.353857e-01,4.130095e-02,4.378068e+00,-3.591705e-01,1.504567e+00,3.938427e-01,5.161734e+00,9.928685e-02,8.626024e-02,"sim_inspiral:simulation_id:0",
         "process:process_id:0","GeneratePPNtwoPN",733733096,735215664,733733096,755475224,733733096,752335605,1.9754580908384590e+01,"MW",8.076584e-01,7.080321e-01,2.489199e-01,1.712161e-02,6.316508e+00,-1.108279e+00,1.305398e+00,2.473332e-01,6.721684e-01,3.424359e-02,3.894549e-02,"sim_inspiral:simulation_id:0",
         "process:process_id:0","GeneratePPNtwoPN",734140880,570285797,734140880,570690706,734140880,576861880,1.3338000410306785e+01,"MW",9.599118e-01,7.008818e-01,2.439186e-01,3.461639e-02,6.429384e+00,-3.086492e-01,1.293048e+00,5.427816e+00,6.706952e-01,1.397947e-01,1.742313e-01,"sim_inspiral:simulation_id:0",
         "process:process_id:0","GeneratePPNtwoPN",734146890,674520016,734146890,695349158,734146890,694126725,1.5012044686819944e+01,"MW",3.392059e-01,8.474727e-01,2.041376e-01,2.641817e-02,5.024578e+00,-6.128079e-01,1.131718e+00,4.411304e+00,3.406950e-01,4.872131e-02,5.080012e-02,"sim_inspiral:simulation_id:0",
         "process:process_id:0","GeneratePPNtwoPN",734331975,648932934,734331975,633438431,734331975,634702809,1.8565300333065291e+01,"MW",7.786215e-01,6.833605e-01,2.489386e-01,2.753212e-02,2.519869e+00,8.785339e-02,3.329763e-01,5.753508e+00,2.169655e+00,3.963500e-02,4.033066e-02,"sim_inspiral:simulation_id:0"
      </Stream>
   </Table>
   <Table Name="sngl_inspiralgroup:sngl_inspiral:table">
      <Column Name="sngl_inspiralgroup:sngl_inspiral:process_id" Type="ilwd:char"/>
      <Column Name="sngl_inspiralgroup:sngl_inspiral:ifo" Type="lstring"/>
      <Column Name="sngl_inspiralgroup:sngl_inspiral:search" Type="lstring"/>
      <Column Name="sngl_inspiralgroup:sngl_inspiral:channel" Type="lstring"/>
      <Column Name="sngl_inspiralgroup:sngl_inspiral:end_time" Type="int_4s"/>
      <Column Name="sngl_inspiralgroup:sngl_inspiral:end_time_ns" Type="int_4s"/>
      <Column Name="sngl_inspiralgroup:sngl_inspiral:end_time_gmst" Type="real_8"/>
      <Column Name="sngl_inspiralgroup:sngl_inspiral:impulse_time" Type="int_4s"/>
      <Column Name="sngl_inspiralgroup:sngl_inspiral:impulse_time_ns" Type="int_4s"/>
      <Column Name="sngl_inspiralgroup:sngl_inspiral:template_duration" Type="real_8"/>
      <Column Name="sngl_inspiralgroup:sngl_inspiral:event_duration" Type="real_8"/>
      <Column Name="sngl_inspiralgroup:sngl_inspiral:amplitude" Type="real_4"/>
      <Column Name="sngl_inspiralgroup:sngl_inspiral:eff_distance" Type="real_4"/>
      <Column Name="sngl_inspiralgroup:sngl_inspiral:coa_phase" Type="real_4"/>
      <Column Name="sngl_inspiralgroup:sngl_inspiral:mass1" Type="real_4"/>
      <Column Name="sngl_inspiralgroup:sngl_inspiral:mass2" Type="real_4"/>
      <Column Name="sngl_inspiralgroup:sngl_inspiral:mchirp" Type="real_4"/>
      <Column Name="sngl_inspiralgroup:sngl_inspiral:eta" Type="real_4"/>
      <Column Name="sngl_inspiralgroup:sngl_inspiral:tau0" Type="real_4"/>
      <Column Name="sngl_inspiralgroup:sngl_inspiral:tau2" Type="real_4"/>
      <Column Name="sngl_inspiralgroup:sngl_inspiral:tau3" Type="real_4"/>
      <Column Name="sngl_inspiralgroup:sngl_inspiral:tau4" Type="real_4"/>
      <Column Name="sngl_inspiralgroup:sngl_inspiral:tau5" Type="real_4"/>
      <Column Name="sngl_inspiralgroup:sngl_inspiral:ttotal" Type="real_4"/>
      <Column Name="sngl_inspiralgroup:sngl_inspiral:psi0" Type="real_4"/>
      <Column Name="sngl_inspiralgroup:sngl_inspiral:psi3" Type="real_4"/>
      <Column Name="sngl_inspiralgroup:sngl_inspiral:f_final" Type="real_4"/>
      <Column Name="sngl_inspiralgroup:sngl_inspiral:snr" Type="real_4"/>
      <Column Name="sngl_inspiralgroup:sngl_inspiral:chisq" Type="real_4"/>
      <Column Name="sngl_inspiralgroup:sngl_inspiral:chisq_dof" Type="int_4s"/>
      <Column Name="sngl_inspiralgroup:sngl_inspiral:sigmasq" Type="real_8"/>
      <Column Name="sngl_inspiralgroup:sngl_inspiral:alpha" Type="real_4"/>
      <Stream Name="sngl_inspiralgroup:sngl_inspiral:table" Type="Local" Delimiter=",">
         "process:process_id:0","H1","FindChirpSPtwoPN","LSC-AS_Q",729649999,878662109,1.0455690452340576e+01,729649999,878662109,8.9851236343383789e+00,9.7656250000000000e-04,0.000000e+00,1.056200e-01,3.098996e-01,5.946192e-01,5.946192e-01,5.176461e-01,2.500000e-01,8.998973e+00,5.223123e-01,3.329593e-01,1.876955e-02,0.000000e+00,9.207096e+00,0.000000e+00,0.000000e+00,0.000000e+00,2.852925e+01,3.283592e+01,15,9.0797311856230376e+00,0.000000e+00,
         "process:process_id:0","H1","FindChirpSPtwoPN","LSC-AS_Q",729675331,306152343,1.7511463404980798e+01,729675331,306152343,2.0446277618408203e+01,1.2207031250000000e-03,0.000000e+00,9.066494e-02,3.966995e-01,6.810157e-01,2.072790e-01,3.163123e-01,1.788950e-01,2.045131e+01,9.112839e-01,5.652069e-01,2.569818e-02,0.000000e+00,2.082308e+01,0.000000e+00,0.000000e+00,0.000000e+00,2.243298e+01,8.649215e+01,15,4.1366890034151584e+00,0.000000e+00,
         "process:process_id:0","H1","FindChirpSPtwoPN","LSC-AS_Q",729789943,224121093,1.4352731358591053e+00,729789943,224121093,5.5243620872497559e+00,1.4648437500000000e-03,0.000000e+00,9.786317e-02,-1.164590e+00,7.926317e-01,7.926317e-01,6.900260e-01,2.500000e-01,5.573638e+00,3.918301e-01,2.748967e-01,1.705466e-02,0.000000e+00,5.707626e+00,0.000000e+00,0.000000e+00,0.000000e+00,3.334710e+01,7.402403e+01,15,1.0650125805215579e+01,0.000000e+00,
         "process:process_id:0","H1","FindChirpSPtwoPN","LSC-AS_Q",729802794,499267578,5.0148455693200233e+00,729802794,499267578,2.3190252304077148e+01,1.2207031250000000e-03,0.000000e+00,7.871877e-02,8.637289e-01,5.194851e-01,2.268844e-01,2.939245e-01,2.115777e-01,2.311292e+01,9.475228e-01,5.367078e-01,2.431896e-02,0.000000e+00,2.354805e+01,0.000000e+00,0.000000e+00,0.000000e+00,1.945163e+01,3.109144e+01,15,2.3445992785176748e+00,0.000000e+00,
         "process:process_id:0","H1","FindChirpSPtwoPN","LSC-AS_Q",730018984,745605468,1.7232111019347276e+01,730018984,745605468,2.8082387924194336e+01,2.8683593750000000e+01,0.000000e+00,9.260558e-02,-1.151915e+00,4.249966e-01,2.183341e-01,2.623115e-01,2.242015e-01,2.793952e+01,1.050280e+00,5.592197e-01,2.462332e-02,0.000000e+00,2.845520e+01,0.000000e+00,0.000000e+00,0.000000e+00,1.580968e+01,3.256549e+01,15,2.1434841789924484e+00,0.000000e+00,
         "process:process_id:0","H1","FindChirpSPtwoPN","LSC-AS_Q",730273978,93994140,1.6257526880221235e+01,730273978,93994140,4.6584224700927734e+00,9.7656250000000000e-04,0.000000e+00,5.029731e-02,1.495602e+00,8.762127e-01,8.762127e-01,7.627875e-01,2.500000e-01,4.716016e+00,3.544538e-01,2.571248e-01,1.649416e-02,0.000000e+00,4.829839e+00,0.000000e+00,0.000000e+00,0.000000e+00,6.944370e+01,7.954233e+01,15,1.2199871060247540e+01,0.000000e+00,
         "process:process_id:0","H1","FindChirpSPtwoPN","LSC-AS_Q",730458852,269287109,1.9752066879934734e+01,730458852,269287109,5.2501239776611328e+00,1.2207031250000000e-03,0.000000e+00,4.772603e-02,2.019881e+00,8.167464e-01,8.167464e-01,7.110190e-01,2.500000e-01,5.302074e+00,3.802612e-01,2.694587e-01,1.688513e-02,0.000000e+00,5.429761e+00,0.000000e+00,0.000000e+00,0.000000e+00,9.385338e+01,1.720407e+02,15,2.0063669124425868e+01,0.000000e+00,
         "process:process_id:0","H1","FindChirpSPtwoPN","LSC-AS_Q",730547646,145263671,2.0484562878612842e+01,730547646,145263671,1.0184669494628906e+01,1.2207031250000000e-03,0.000000e+00,2.580109e-01,-2.055001e+00,9.553602e-01,3.335964e-01,4.786141e-01,1.918280e-01,1.025507e+01,5.933834e-01,4.112504e-01,2.163320e-02,0.000000e+00,1.045884e+01,0.000000e+00,0.000000e+00,0.000000e+00,1.032078e+01,2.007546e+01,15,7.0909040673075756e+00,0.000000e+00,
         "process:process_id:0","H1","FindChirpSPtwoPN","LSC-AS_Q",730700689,764404296,1.5113073613312510e+01,730700689,764404296,4.5555660247802734e+01,9.7656250000000000e-04,0.000000e+00,4.647735e-02,-2.905625e+00,2.257359e-01,2.257358e-01,1.965145e-01,2.500000e-01,4.521234e+01,1.375842e+00,6.350629e-01,2.592189e-02,0.000000e+00,4.597904e+01,0.000000e+00,0.000000e+00,0.000000e+00,3.148752e+01,7.753752e+01,15,2.1417050015341217e+00,0.000000e+00,
         "process:process_id:0","H1","FindChirpSPtwoPN","LSC-AS_Q",730713466,670898437,1.8671931538031334e+01,730713466,670898437,8.5858554840087891e+00,1.2207031250000000e-03,0.000000e+00,7.308929e-02,1.399539e+00,6.108550e-01,6.108549e-01,5.317801e-01,2.500000e-01,8.603880e+00,5.084299e-01,3.270331e-01,1.860176e-02,0.000000e+00,8.803879e+00,0.000000e+00,0.000000e+00,0.000000e+00,4.457155e+01,3.038166e+01,15,1.0612628479118696e+01,0.000000e+00,
         "process:process_id:0","H1","FindChirpSPtwoPN","LSC-AS_Q",730720152,969482421,2.0534321836597389e+01,730720152,969482421,8.6310501098632812e+00,1.4648437500000000e-03,0.000000e+00,1.593176e-01,1.896876e+00,6.089577e-01,6.089576e-01,5.301285e-01,2.500000e-01,8.648603e+00,5.100139e-01,3.277120e-01,1.862106e-02,0.000000e+00,8.849526e+00,0.000000e+00,0.000000e+00,0.000000e+00,2.081350e+01,2.731170e+01,15,1.0995571993613055e+01,0.000000e+00,
         "process:process_id:0","H1","FindChirpSPtwoPN","LSC-AS_Q",731006452,49560546,4.2795832308381794e+00,731006452,49560546,1.1157644271850586e+01,1.7089843750000000e-03,0.000000e+00,8.029423e-02,1.973715e+00,9.229044e-01,3.109303e-01,4.533572e-01,1.884976e-01,1.122484e+01,6.287357e-01,4.308901e-01,2.221427e-02,0.000000e+00,1.144490e+01,0.000000e+00,0.000000e+00,0.000000e+00,2.966583e+01,5.855675e+01,15,5.6739019665755093e+00,0.000000e+00,
         "process:process_id:0","H1","FindChirpSPtwoPN","LSC-AS_Q",731165965,936767578,7.1031148516469533e-01,731165965,936767578,5.7823076248168945e+00,1.2207031250000000e-03,0.000000e+00,6.239676e-02,1.470814e+00,9.254628e-01,6.465777e-01,6.712666e-01,2.421320e-01,5.835652e+00,4.049202e-01,2.854187e-01,1.743292e-02,0.000000e+00,5.972587e+00,0.000000e+00,0.000000e+00,0.000000e+00,6.878539e+01,3.868518e+01,15,1.8421137335398413e+01,0.000000e+00,
         "process:process_id:0","H1","FindChirpSPtwoPN","LSC-AS_Q",731171983,64941406,2.3863121983160576e+00,731171983,64941406,1.1424629211425781e+01,1.7089843750000000e-03,0.000000e+00,1.461744e-01,4.246469e-01,7.052816e-01,3.829588e-01,4.482949e-01,2.280683e-01,1.143690e+01,6.126582e-01,3.872240e-01,2.044508e-02,0.000000e+00,1.168278e+01,0.000000e+00,0.000000e+00,0.000000e+00,2.052966e+01,4.262822e+01,15,9.0054658064462192e+00,0.000000e+00,
         "process:process_id:0","H1","FindChirpSPtwoPN","LSC-AS_Q",731274171,934814453,6.8498271218728686e+00,731274171,934814453,3.4869785308837891e+01,1.2207031250000000e-03,0.000000e+00,2.611866e-02,2.765312e+00,3.668890e-01,1.948598e-01,2.304866e-01,2.265545e-01,3.466078e+01,1.193042e+00,6.057727e-01,2.559332e-02,0.000000e+00,3.527364e+01,0.000000e+00,0.000000e+00,0.000000e+00,5.951987e+01,4.803170e+02,15,2.4167165183527120e+00,0.000000e+00,
         "process:process_id:0","H1","FindChirpSPtwoPN","LSC-AS_Q",731306231,776367187,1.5779721148370040e+01,731306231,776367187,3.2957626342773438e+01,1.2207031250000000e-03,0.000000e+00,5.276221e-02,-1.634259e+00,3.837136e-01,1.995612e-01,2.383831e-01,2.250800e-01,3.276842e+01,1.154885e+00,5.946453e-01,2.537838e-02,0.000000e+00,3.335404e+01,0.000000e+00,0.000000e+00,0.000000e+00,3.140558e+01,5.102204e+01,15,2.7457413261448447e+00,0.000000e+00,
         "process:process_id:0","H1","FindChirpSPtwoPN","LSC-AS_Q",731312036,757080078,1.7396630652579997e+01,731312036,757080078,2.9974143981933594e+01,9.7656250000000000e-04,0.000000e+00,5.132048e-02,2.554287e+00,4.708185e-01,1.857222e-01,2.521031e-01,2.028589e-01,2.985046e+01,1.113816e+00,6.097361e-01,2.609118e-02,0.000000e+00,3.038063e+01,0.000000e+00,0.000000e+00,0.000000e+00,3.287180e+01,4.689001e+01,15,2.8459579743715824e+00,0.000000e+00,
         "process:process_id:0","H1","FindChirpSPtwoPN","LSC-AS_Q",731598864,861816406,1.2892456778470014e+00,731598864,861816406,2.3403043746948242e+01,0.0000000000000000e+00,0.000000e+00,2.569324e-01,4.670367e-01,5.836109e-01,2.033973e-01,2.920689e-01,1.916505e-01,2.335818e+01,9.725657e-01,5.719361e-01,2.551605e-02,0.000000e+00,2.378433e+01,0.000000e+00,0.000000e+00,0.000000e+00,7.104491e+00,2.139634e+01,15,3.3319902271777262e+00,0.000000e+00,
         "process:process_id:0","H1","FindChirpSPtwoPN","LSC-AS_Q",731605059,243408203,3.0146182402264743e+00,731605059,243408203,5.6613168716430664e+00,1.2207031250000000e-03,0.000000e+00,1.164865e-01,-1.579344e+00,9.993128e-01,6.163778e-01,6.792935e-01,2.359565e-01,5.721179e+00,4.019057e-01,2.875894e-01,1.754835e-02,0.000000e+00,5.853043e+00,0.000000e+00,0.000000e+00,0.000000e+00,3.121385e+01,3.761665e+01,15,1.3220434233518159e+01,0.000000e+00,
         "process:process_id:0","H1","FindChirpSPtwoPN","LSC-AS_Q",731669088,560058593,2.0849235778459246e+01,731669088,560058593,1.4413523674011230e+01,9.7656250000000000e-04,0.000000e+00,4.553777e-02,-3.007272e+00,9.053235e-01,2.394083e-01,3.888885e-01,1.654000e-01,1.449459e+01,7.543386e-01,5.162250e-01,2.496641e-02,0.000000e+00,1.475767e+01,0.000000e+00,0.000000e+00,0.000000e+00,5.714273e+01,1.432539e+02,15,6.7711994227592811e+00,0.000000e+00,
         "process:process_id:0","H1","FindChirpSPtwoPN","LSC-AS_Q",731675455,973388671,2.2622804317639932e+01,731675455,973388671,5.9383320808410645e+00,1.4648437500000000e-03,0.000000e+00,9.697072e-02,2.626003e+00,7.595931e-01,7.595930e-01,6.612642e-01,2.500000e-01,5.983512e+00,4.088728e-01,2.828111e-01,1.729842e-02,0.000000e+00,6.126873e+00,0.000000e+00,0.000000e+00,0.000000e+00,4.087952e+01,3.603047e+01,15,1.5714224462717334e+01,0.000000e+00,
         "process:process_id:0","H1","FindChirpSPtwoPN","LSC-AS_Q",731700744,458251953,5.6666161011821696e+00,731700744,458251953,1.0142492294311523e+01,9.7656250000000000e-04,0.000000e+00,1.005367e-01,1.345625e+00,5.533806e-01,5.533805e-01,4.817458e-01,2.500000e-01,1.014420e+01,5.612357e-01,3.493021e-01,1.922467e-02,0.000000e+00,1.037536e+01,0.000000e+00,0.000000e+00,0.000000e+00,2.888703e+01,3.644894e+01,15,8.4344108742953114e+00,0.000000e+00,
         "process:process_id:0","H1","FindChirpSPtwoPN","LSC-AS_Q",731719791,578369140,1.0971968732347920e+01,731719791,578369140,6.2883810997009277e+00,1.2207031250000000e-03,0.000000e+00,6.957781e-02,-4.236721e-01,7.343619e-01,7.343618e-01,6.392991e-01,2.500000e-01,6.330058e+00,4.229208e-01,2.892524e-01,1.749431e-02,0.000000e+00,6.481220e+00,0.000000e+00,0.000000e+00,0.000000e+00,5.464206e+01,4.642872e+01,15,1.4454253298204533e+01,0.000000e+00,
         "process:process_id:0","H1","FindChirpSPtwoPN","LSC-AS_Q",731732742,158691406,1.4579201444300512e+01,731732742,158691406,1.8992872238159180e+01,1.9531250000000000e-03,0.000000e+00,1.036452e-01,-1.377076e+00,6.644468e-01,2.292789e-01,3.307149e-01,1.907286e-01,1.898854e+01,8.597771e-01,5.279893e-01,2.453744e-02,0.000000e+00,1.934487e+01,0.000000e+00,0.000000e+00,0.000000e+00,2.019497e+01,4.588771e+01,15,4.3811167269039899e+00,0.000000e+00,
         "process:process_id:0","H1","FindChirpSPtwoPN","LSC-AS_Q",731828527,677246093,1.7259137739514312e+01,731828527,677246093,2.1597230911254883e+01,1.7089843750000000e-03,0.000000e+00,1.640326e-01,2.518235e-01,6.424585e-01,2.049460e-01,3.062475e-01,1.833593e-01,2.158375e+01,9.362315e-01,5.690455e-01,2.566136e-02,0.000000e+00,2.197660e+01,0.000000e+00,0.000000e+00,0.000000e+00,1.373117e+01,4.275268e+01,15,5.0731293404038045e+00,0.000000e+00,
         "process:process_id:0","H1","FindChirpSPtwoPN","LSC-AS_Q",731834363,806152343,1.8884723202693795e+01,731834363,806152343,1.7623666763305664e+01,1.2207031250000000e-03,0.000000e+00,7.002764e-02,-4.673598e-02,5.860404e-01,2.774400e-01,3.462641e-01,2.180679e-01,1.758877e+01,7.997157e-01,4.725166e-01,2.271906e-02,0.000000e+00,1.793868e+01,0.000000e+00,0.000000e+00,0.000000e+00,3.568719e+01,5.285548e+01,15,6.2454505872254895e+00,0.000000e+00,
         "process:process_id:0","H1","FindChirpSPtwoPN","LSC-AS_Q",731891938,789306640,1.0921561610744231e+01,731891938,789306640,6.9331541061401367e+00,1.2207031250000000e-03,0.000000e+00,1.491133e-01,-2.804559e-01,1.078109e+00,4.586744e-01,6.014199e-01,2.093832e-01,7.008389e+00,4.640017e-01,3.350890e-01,1.924594e-02,0.000000e+00,7.156548e+00,0.000000e+00,0.000000e+00,0.000000e+00,2.489431e+01,4.912381e+01,15,1.3779495615310406e+01,0.000000e+00,
         "process:process_id:0","H1","FindChirpSPtwoPN","LSC-AS_Q",731898119,340576171,1.2643081893229651e+01,731898119,340576171,2.0818843841552734e+01,1.4648437500000000e-03,0.000000e+00,1.132859e-01,-9.537429e-01,4.831119e-01,2.731346e-01,3.137054e-01,2.307266e-01,2.073534e+01,8.737034e-01,4.878697e-01,2.291613e-02,0.000000e+00,2.114409e+01,0.000000e+00,0.000000e+00,0.000000e+00,1.921518e+01,2.647896e+01,15,4.7384943166774720e+00,0.000000e+00,
         "process:process_id:0","H1","FindChirpSPtwoPN","LSC-AS_Q",731910818,803955078,1.6180368944435482e+01,731910818,803955078,8.6545438766479492e+00,1.4648437500000000e-03,0.000000e+00,2.545602e-01,2.738975e+00,7.031495e-01,5.275014e-01,5.290976e-01,2.449072e-01,8.676705e+00,5.127426e-01,3.322148e-01,1.878590e-02,0.000000e+00,8.876019e+00,0.000000e+00,0.000000e+00,0.000000e+00,1.328933e+01,2.833074e+01,15,1.1444253622655829e+01,0.000000e+00,
         "process:process_id:0","H1","FindChirpSPtwoPN","LSC-AS_Q",731917447,727294921,1.8026778033156361e+01,731917447,727294921,7.1019234657287598e+00,1.2207031250000000e-03,0.000000e+00,1.500026e-01,-1.846385e+00,1.051736e+00,4.564649e-01,5.930573e-01,2.110551e-01,7.173869e+00,4.698238e-01,3.366215e-01,1.926671e-02,0.000000e+00,7.326338e+00,0.000000e+00,0.000000e+00,0.000000e+00,2.509788e+01,5.138887e+01,15,1.4173330354300765e+01,0.000000e+00,
         "process:process_id:0","H1","FindChirpSPtwoPN","LSC-AS_Q",731936624,71777343,2.3368124588963887e+01,731936624,71777343,2.2030384063720703e+01,1.2207031250000000e-03,0.000000e+00,4.179471e-02,1.201395e+00,4.306304e-01,2.844675e-01,3.033957e-01,2.395556e-01,2.192295e+01,8.975171e-01,4.877460e-01,2.281493e-02,0.000000e+00,2.235553e+01,0.000000e+00,0.000000e+00,0.000000e+00,5.282245e+01,3.385849e+01,15,4.8739347568228757e+00,0.000000e+00,
         "process:process_id:0","H1","FindChirpSPtwoPN","LSC-AS_Q",731949076,18310546,2.8364687119010421e+00,731949076,18310546,1.3582748413085938e+01,1.2207031250000000e-03,0.000000e+00,1.008772e-01,1.348262e+00,6.381105e-01,3.447181e-01,4.045018e-01,2.277217e-01,1.357418e+01,6.791722e-01,4.150695e-01,2.117145e-02,0.000000e+00,1.385946e+01,0.000000e+00,0.000000e+00,0.000000e+00,2.659962e+01,2.630763e+01,15,7.2000775572973525e+00,0.000000e+00,
         "process:process_id:0","H1","FindChirpSPtwoPN","LSC-AS_Q",731994118,176269531,1.5382435180664890e+01,731994118,176269531,1.0247857093811035e+01,9.7656250000000000e-04,0.000000e+00,6.999694e-02,-9.588683e-01,5.499960e-01,5.499960e-01,4.787993e-01,2.500000e-01,1.024846e+01,5.646895e-01,3.507336e-01,1.926402e-02,0.000000e+00,1.048168e+01,0.000000e+00,0.000000e+00,0.000000e+00,4.525544e+01,6.083264e+01,15,1.0034589654924003e+01,0.000000e+00,
         "process:process_id:0","H1","FindChirpSPtwoPN","LSC-AS_Q",732350508,787597656,1.8650873109706573e+01,732350508,787597656,1.3464586257934570e+01,1.7089843750000000e-03,0.000000e+00,2.235831e-01,-2.365898e+00,7.833213e-01,2.908871e-01,4.058644e-01,1.974637e-01,1.349832e+01,6.956013e-01,4.511255e-01,2.254338e-02,0.000000e+00,1.376534e+01,0.000000e+00,0.000000e+00,0.000000e+00,1.199455e+01,3.131040e+01,15,7.1919440932342091e+00,0.000000e+00,
         "process:process_id:0","H1","FindChirpSPtwoPN","LSC-AS_Q",732497033,883789062,1.1463725498264862e+01,732497033,883789062,1.0504352569580078e+01,9.7656250000000000e-04,0.000000e+00,9.818973e-02,-2.906888e+00,7.175865e-01,4.145867e-01,4.713149e-01,2.320940e-01,1.052113e+01,5.809273e-01,3.705993e-01,1.995879e-02,0.000000e+00,1.075142e+01,0.000000e+00,0.000000e+00,0.000000e+00,3.328143e+01,5.073454e+01,15,1.0679136452428994e+01,0.000000e+00,
         "process:process_id:0","H1","FindChirpSPtwoPN","LSC-AS_Q",732548139,455322265,1.6985849275895291e+00,732548139,455322265,8.1746253967285156e+00,9.7656250000000000e-04,0.000000e+00,1.025859e-01,2.592818e+00,7.944453e-01,5.021372e-01,5.469804e-01,2.372936e-01,8.209086e+00,4.986388e-01,3.311496e-01,1.881856e-02,0.000000e+00,8.395394e+00,0.000000e+00,0.000000e+00,0.000000e+00,3.657655e+01,5.623927e+01,15,1.4079284415235453e+01,0.000000e+00,
         "process:process_id:0","H1","FindChirpSPtwoPN","LSC-AS_Q",732586023,220703125,1.2250664845117264e+01,732586023,220703125,1.6757505416870117e+01,1.2207031250000000e-03,0.000000e+00,1.016779e-01,6.609707e-01,4.908420e-01,3.451546e-01,3.572172e-01,2.424077e-01,1.669913e+01,7.607623e-01,4.343379e-01,2.150262e-02,0.000000e+00,1.704706e+01,0.000000e+00,0.000000e+00,0.000000e+00,2.800850e+01,4.139142e+01,15,8.1102220987736207e+00,0.000000e+00,
         "process:process_id:0","H1","FindChirpSPtwoPN","LSC-AS_Q",733076652,707763671,4.9097721010446547e+00,733076652,707763671,1.1461877822875977e+01,1.4648437500000000e-03,0.000000e+00,4.047349e-02,-2.084786e+00,9.025965e-01,3.076649e-01,4.462386e-01,1.895890e-01,1.152487e+01,6.379928e-01,4.339547e-01,2.226955e-02,0.000000e+00,1.175118e+01,0.000000e+00,0.000000e+00,0.000000e+00,8.856884e+01,1.344072e+02,15,1.2850004977066718e+01,0.000000e+00,
         "process:process_id:0","H1","FindChirpSPtwoPN","LSC-AS_Q",733089736,876708984,8.5542143818197971e+00,733089736,876708984,2.4165393829345703e+01,9.7656250000000000e-04,0.000000e+00,2.839604e-01,3.078918e+00,5.924604e-01,1.939407e-01,2.864627e-01,1.857976e-01,2.412502e+01,9.980765e-01,5.902568e-01,2.606969e-02,0.000000e+00,2.455891e+01,0.000000e+00,0.000000e+00,0.000000e+00,8.742727e+00,2.789256e+01,15,6.1632467609424815e+00,0.000000e+00,
         "process:process_id:0","H1","FindChirpSPtwoPN","LSC-AS_Q",733376021,249755859,1.6295379295994838e+01,733376021,249755859,5.5951275825500488e+00,1.2207031250000000e-03,0.000000e+00,2.193557e-01,-3.768449e-01,7.867124e-01,7.867123e-01,6.848729e-01,2.500000e-01,5.643708e+00,3.947782e-01,2.762738e-01,1.709732e-02,0.000000e+00,5.779310e+00,0.000000e+00,0.000000e+00,0.000000e+00,2.310130e+01,4.755737e+01,15,2.5678563445448550e+01,0.000000e+00,
         "process:process_id:0","H1","FindChirpSPtwoPN","LSC-AS_Q",733452386,590576171,1.3566052137853370e+01,733452386,590576171,1.3059380531311035e+01,1.2207031250000000e-03,0.000000e+00,8.392276e-02,-2.018004e+00,8.292457e-01,2.865959e-01,4.130964e-01,1.908746e-01,1.310677e+01,6.882070e-01,4.550167e-01,2.277563e-02,0.000000e+00,1.336273e+01,0.000000e+00,0.000000e+00,0.000000e+00,3.475610e+01,5.977802e+01,15,8.5078813570386771e+00,0.000000e+00,
         "process:process_id:0","H1","FindChirpSPtwoPN","LSC-AS_Q",733465184,20996093,1.7130626751581829e+01,733465184,20996093,1.3433479309082031e+01,1.2207031250000000e-03,0.000000e+00,1.717192e-01,-5.534067e-01,5.722993e-01,3.857297e-01,4.074441e-01,2.405188e-01,1.341120e+01,6.678633e-01,3.997382e-01,2.064539e-02,0.000000e+00,1.369997e+01,0.000000e+00,0.000000e+00,0.000000e+00,1.753276e+01,3.071241e+01,15,9.0643921350059848e+00,0.000000e+00,
         "process:process_id:0","H1","FindChirpSPtwoPN","LSC-AS_Q",733548028,77880859,1.6205870202701124e+01,733548028,77880859,1.1390196800231934e+01,1.4648437500000000e-03,0.000000e+00,1.402583e-01,-2.380009e+00,5.165318e-01,5.165318e-01,4.496671e-01,2.500000e-01,1.137879e+01,6.012735e-01,3.657231e-01,1.967136e-02,0.000000e+00,1.163401e+01,0.000000e+00,0.000000e+00,0.000000e+00,2.484356e+01,3.507114e+01,15,1.2141848546147923e+01,0.000000e+00,
         "process:process_id:0","H1","FindChirpSPtwoPN","LSC-AS_Q",733611869,446044921,9.9881368759481450e+00,733611869,446044921,4.8790607452392578e+00,8.3203125000000000e-01,0.000000e+00,1.149561e-02,-2.258984e+00,8.527172e-01,8.527171e-01,7.423334e-01,2.500000e-01,4.934573e+00,3.642204e-01,2.618266e-01,1.664428e-02,0.000000e+00,5.053610e+00,0.000000e+00,0.000000e+00,0.000000e+00,4.225663e+02,2.639336e+03,15,2.3596849224343106e+01,0.000000e+00,
         "process:process_id:0","H1","FindChirpSPtwoPN","LSC-AS_Q",733637465,625000000,1.7117653249754675e+01,733637465,625000000,3.8578279018402100e+00,1.2207031250000000e-03,0.000000e+00,1.378330e-01,5.413757e-02,9.786019e-01,9.786018e-01,8.519224e-01,2.500000e-01,3.922664e+00,3.173680e-01,2.388616e-01,1.589760e-02,0.000000e+00,4.017068e+00,0.000000e+00,0.000000e+00,0.000000e+00,4.175386e+01,4.654660e+01,15,3.3120697093749968e+01,0.000000e+00,
         "process:process_id:0","H1","FindChirpSPtwoPN","LSC-AS_Q",733701259,234619140,1.0886617350710763e+01,733701259,234619140,1.0847670555114746e+01,1.2207031250000000e-03,0.000000e+00,9.596258e-02,-1.713037e-01,5.317283e-01,5.317283e-01,4.628963e-01,2.500000e-01,1.084197e+01,5.840895e-01,3.587213e-01,1.948215e-02,0.000000e+00,1.108682e+01,0.000000e+00,0.000000e+00,0.000000e+00,3.888391e+01,7.152943e+01,15,1.3923351611087572e+01,0.000000e+00,
         "process:process_id:0","H1","FindChirpSPtwoPN","LSC-AS_Q",733733096,755859375,1.9754586657302248e+01,733733096,755859375,5.9883604049682617e+00,9.7656250000000000e-04,0.000000e+00,3.454322e-02,-1.747226e+00,7.558451e-01,7.558451e-01,6.580014e-01,2.500000e-01,6.033044e+00,4.109002e-01,2.837452e-01,1.732697e-02,0.000000e+00,6.177526e+00,0.000000e+00,0.000000e+00,0.000000e+00,1.374957e+02,3.324963e+02,15,2.2558169318176464e+01,0.000000e+00,
         "process:process_id:0","H1","FindChirpSPtwoPN","LSC-AS_Q",734140880,571533203,1.3338000757706663e+01,734140880,571533203,5.2325587272644043e+00,1.2207031250000000e-03,0.000000e+00,1.419273e-01,1.878146e+00,8.183582e-01,8.183581e-01,7.124222e-01,2.500000e-01,5.284681e+00,3.795122e-01,2.691048e-01,1.687404e-02,0.000000e+00,5.411963e+00,0.000000e+00,0.000000e+00,0.000000e+00,3.194983e+01,5.848581e+01,15,2.0562187213476111e+01,0.000000e+00,
         "process:process_id:0","H1","FindChirpSPtwoPN","LSC-AS_Q",734146890,696044921,1.5012050682281455e+01,734146890,696044921,1.1017815589904785e+01,9.7656250000000000e-04,0.000000e+00,4.962912e-02,-5.979128e-01,7.931865e-01,3.592241e-01,4.576390e-01,2.145489e-01,1.105035e+01,6.069438e-01,3.961983e-01,2.085174e-02,0.000000e+00,1.128195e+01,0.000000e+00,0.000000e+00,0.000000e+00,6.577981e+01,8.579484e+01,15,1.0657574121415582e+01,0.000000e+00,
         "process:process_id:0","H1","FindChirpSPtwoPN","LSC-AS_Q",734331975,633544921,1.8565296040988631e+01,734331975,633544921,6.3617281913757324e+00,1.2207031250000000e-03,0.000000e+00,4.021480e-02,2.334827e+00,7.293542e-01,7.293542e-01,6.349397e-01,2.500000e-01,6.402659e+00,4.258246e-01,2.905749e-01,1.753425e-02,0.000000e+00,6.555443e+00,0.000000e+00,0.000000e+00,0.000000e+00,1.094071e+02,1.255752e+02,15,1.9358107243502783e+01,0.000000e+00
      </Stream>
   </Table>
</LIGO_LW>