<?xml version='1.0' encoding='utf-8' ?>
<!DOCTYPE LIGO_LW [
<!ELEMENT LIGO_LW ((LIGO_LW|Comment|Param|Table|Array|Stream|IGWDFrame|AdcData|AdcInterval|Time|Detector)*)>
<!ATTLIST LIGO_LW
         Name CDATA #IMPLIED
         Type CDATA #IMPLIED>

<!ELEMENT Comment (#PCDATA)>

<!ELEMENT Param (#PCDATA|Comment)*>
<!ATTLIST Param 
         Name CDATA #IMPLIED
         Type CDATA #IMPLIED
         Start CDATA #IMPLIED
         Scale CDATA #IMPLIED
         Unit CDATA #IMPLIED
         DataUnit CDATA #IMPLIED>

<!ELEMENT Table (Comment?,Column*,Stream?)>
<!ATTLIST Table 
         Name CDATA #IMPLIED
         Type CDATA #IMPLIED>

<!ELEMENT Column EMPTY>
<!ATTLIST Column
         Name CDATA #IMPLIED
         Type CDATA #IMPLIED
         Unit CDATA #IMPLIED>

<!ELEMENT Array (Dim*,Stream?)>
<!ATTLIST Array 
         Name CDATA #IMPLIED
         Type CDATA #IMPLIED
         Unit CDATA #IMPLIED>

<!ELEMENT Dim (#PCDATA)>
<!ATTLIST Dim 
         Name  CDATA #IMPLIED
         Unit CDATA #IMPLIED
         Start CDATA #IMPLIED
         Scale CDATA #IMPLIED>

<!ELEMENT Stream (#PCDATA)>
<!ATTLIST Stream 
         Name      CDATA #IMPLIED
         Type      (Remote|Local) "Local"
         Delimiter CDATA ","
         Encoding  CDATA #IMPLIED
         Content   CDATA #IMPLIED>

<!ELEMENT IGWDFrame ((Comment|Param|Time|Detector|AdcData|LIGO_LW|Stream?|Array|IGWDFrame)*)>
<!ATTLIST IGWDFrame 
         Name CDATA #IMPLIED>

<!ELEMENT Detector ((Comment|Param|LIGO_LW)*)>
<!ATTLIST Detector 
         Name CDATA #IMPLIED>

<!ELEMENT AdcData ((AdcData|Comment|Param|Time|LIGO_LW|Array)*)>
<!ATTLIST AdcData 
         Name CDATA #IMPLIED>

<!ELEMENT AdcInterval ((AdcData|Comment|Time)*)>
<!ATTLIST AdcInterval 
         Name CDATA #IMPLIED
         StartTime CDATA #IMPLIED
         DeltaT CDATA #IMPLIED>

<!ELEMENT Time (#PCDATA)>
<!ATTLIST Time 
         Name CDATA #IMPLIED
         Type (GPS|Unix|ISO-8601) "ISO-8601">
]>

<LIGO_LW>
   <Comment>metadata</Comment>
   <Table Name="processgroup:process:table">
      <Column Name="processgroup:process:program" Type="lstring"/>
      <Column Name="processgroup:process:version" Type="lstring"/>
      <Column Name="processgroup:process:cvs_repository" Type="lstring"/>
      <Column Name="processgroup:process:cvs_entry_time" Type="int_4s"/>
      <Column Name="processgroup:process:comment" Type="lstring"/>
      <Column Name="processgroup:process:is_online" Type="int_4s"/>
      <Column Name="processgroup:process:node" Type="lstring"/>
      <Column Name="processgroup:process:username" Type="lstring"/>
      <Column Name="processgroup:process:unix_procid" Type="int_4s"/>
      <Column Name="processgroup:process:start_time" Type="int_4s"/>
      <Column Name="processgroup:process:end_time" Type="int_4s"/>
      <Column Name="processgroup:process:jobid" Type="int_4s"/>
      <Column Name="processgroup:process:domain" Type="lstring"/>
      <Column Name="processgroup:process:ifos" Type="lstring"/>
      <Column Name="processgroup:process:process_id" Type="ilwd:char"/>
      <Stream Name="processgroup:process:table" Type="Local" Delimiter=",">
         "sire","1.15","/usr/local/cvs/lscsoft/lalapps/src/inspiral/sire.c\,v",769623277," ",0,"ldas-grid.ligo.caltech.edu","dbrown",23476,776376234,776376236,0,"lalapps","","process:process_id:0"
      </Stream>
   </Table>
   <Table Name="process_paramsgroup:process_params:table">
      <Column Name="process_paramsgroup:process_params:program" Type="lstring"/>
      <Column Name="process_paramsgroup:process_params:process_id" Type="ilwd:char"/>
      <Column Name="process_paramsgroup:process_params:param" Type="lstring"/>
      <Column Name="process_paramsgroup:process_params:type" Type="lstring"/>
      <Column Name="process_paramsgroup:process_params:value" Type="lstring"/>
      <Stream Name="process_paramsgroup:process_params:table" Type="Local" Delimiter=",">
         "sire","process:process_id:0","--playground-only","string"," ",
         "sire","process:process_id:0","--input","string","h1-inca_l1h1h2.files",
         "sire","process:process_id:0","--output","string","h1-inca_l1h1h2_inj_clust.xml",
         "sire","process:process_id:0","--debug-level","string","33",
         "sire","process:process_id:0","--injection-coincidence","int","5",
         "sire","process:process_id:0","--cluster-time","int","16",
         "sire","process:process_id:0","--cluster-algorithm","string","snr",
         "sire","process:process_id:0","--injection-file","string","HL-INJECTIONS_2375-729273613-5094000.xml"
      </Stream>
   </Table>
   <Table Name="sim_inspiralgroup:sim_inspiral:table">
      <Column Name="sim_inspiralgroup:sim_inspiral:process_id" Type="ilwd:char"/>
      <Column Name="sim_inspiralgroup:sim_inspiral:waveform" Type="lstring"/>
      <Column Name="sim_inspiralgroup:sim_inspiral:geocent_end_time" Type="int_4s"/>
      <Column Name="sim_inspiralgroup:sim_inspiral:geocent_end_time_ns" Type="int_4s"/>
      <Column Name="sim_inspiralgroup:sim_inspiral:h_end_time" Type="int_4s"/>
      <Column Name="sim_inspiralgroup:sim_inspiral:h_end_time_ns" Type="int_4s"/>
      <Column Name="sim_inspiralgroup:sim_inspiral:l_end_time" Type="int_4s"/>
      <Column Name="sim_inspiralgroup:sim_inspiral:l_end_time_ns" Type="int_4s"/>
      <Column Name="sim_inspiralgroup:sim_inspiral:end_time_gmst" Type="real_8"/>
      <Column Name="sim_inspiralgroup:sim_inspiral:source" Type="lstring"/>
      <Column Name="sim_inspiralgroup:sim_inspiral:mass1" Type="real_4"/>
      <Column Name="sim_inspiralgroup:sim_inspiral:mass2" Type="real_4"/>
      <Column Name="sim_inspiralgroup:sim_inspiral:eta" Type="real_4"/>
      <Column Name="sim_inspiralgroup:sim_inspiral:distance" Type="real_4"/>
      <Column Name="sim_inspiralgroup:sim_inspiral:longitude" Type="real_4"/>
      <Column Name="sim_inspiralgroup:sim_inspiral:latitude" Type="real_4"/>
      <Column Name="sim_inspiralgroup:sim_inspiral:inclination" Type="real_4"/>
      <Column Name="sim_inspiralgroup:sim_inspiral:coa_phase" Type="real_4"/>
      <Column Name="sim_inspiralgroup:sim_inspiral:polarization" Type="real_4"/>
      <Column Name="sim_inspiralgroup:sim_inspiral:eff_dist_h" Type="real_4"/>
      <Column Name="sim_inspiralgroup:sim_inspiral:eff_dist_l" Type="real_4"/>
      <Column Name="sim_inspiralgroup:sim_inspiral:simulation_id" Type="ilwd:char"/>
      <Stream Name="sim_inspiralgroup:sim_inspiral:table" Type="Local" Delimiter=",">
         "process:process_id:0","GeneratePPNtwoPN",729337420,610073686,729337420,594296021,729337420,602230326,1.9390389816773435e+01,"MW",3.548730e-01,6.425403e-01,2.292044e-01,4.026111e-02,1.777158e+00,1.027299e+00,2.015626e+00,4.346896e+00,5.678402e+00,1.094759e-01,1.482666e-01,"sim_inspiral:simulation_id:0",
         "process:process_id:0","GeneratePPNtwoPN",729344213,971276760,729344213,960907298,729344213,953612660,2.1282601158014604e+01,"MW",6.754412e-01,5.513664e-01,2.474429e-01,1.749283e-02,4.478826e+00,1.588896e-01,2.511672e+00,3.324995e+00,2.455989e+00,4.274363e-02,2.592862e-02,"sim_inspiral:simulation_id:0",
         "process:process_id:0","GeneratePPNtwoPN",729388704,726932526,729388704,735650688,729388704,743524483,9.6749809574666958e+00,"MW",7.548725e-01,7.376698e-01,2.499668e-01,3.883345e-02,4.626000e+00,-8.182314e-02,1.800541e+00,4.119125e+00,4.620616e+00,1.911727e-01,1.034980e-01,"sim_inspiral:simulation_id:0",
         "process:process_id:0","GeneratePPNtwoPN",729413808,89573562,729413808,105030998,729413808,97999488,1.6667229119286770e+01,"MW",8.605790e-01,7.640019e-01,2.491165e-01,3.686567e-02,4.048207e+00,-1.242768e+00,1.796753e+00,2.457076e+00,4.915538e+00,9.324581e-02,1.327482e-01,"sim_inspiral:simulation_id:0",
         "process:process_id:0","GeneratePPNtwoPN",729433362,270999432,729433362,284260544,729433362,277138905,2.2113817736204300e+01,"MW",8.519034e-01,8.141980e-01,2.498720e-01,3.365684e-02,4.986544e+00,-1.252375e+00,2.261693e+00,2.573849e+00,5.648090e+00,7.071839e-02,8.902166e-02,"sim_inspiral:simulation_id:0",
         "process:process_id:0","GeneratePPNtwoPN",729452123,235891342,729452123,230016998,729452123,223473657,3.3394651493057608e+00,"MW",8.645250e-01,4.412910e-01,2.237374e-01,3.737122e-02,5.528280e+00,-4.154685e-01,1.802849e+00,2.635933e+00,5.226516e+00,2.722706e-01,2.565407e-01,"sim_inspiral:simulation_id:0",
         "process:process_id:0","GeneratePPNtwoPN",729541543,737199783,729541543,751031274,729541543,742686041,4.2465002954171762e+00,"MW",7.175733e-01,9.602661e-01,2.447694e-01,2.388880e-02,1.107011e+00,-5.202612e-01,7.389112e-01,1.793884e+00,1.025266e-01,4.806668e-02,1.222701e-01,"sim_inspiral:simulation_id:0",
         "process:process_id:0","GeneratePPNtwoPN",729554016,982474208,729554016,982125471,729554016,991388593,7.7207769439576399e+00,"MW",2.249418e-01,6.540967e-01,1.904129e-01,4.240823e-02,4.049142e+00,5.156413e-01,1.876742e-01,5.798090e+00,4.772100e+00,9.169134e-02,7.493660e-02,"sim_inspiral:simulation_id:0",
         "process:process_id:0","GeneratePPNtwoPN",729592706,415105343,729592706,395349893,729592706,398314493,1.8497266041744087e+01,"MW",8.706098e-01,9.915199e-01,2.489460e-01,2.944991e-02,2.966943e+00,1.166981e+00,4.215480e-01,3.980879e+00,4.842751e+00,3.462332e-02,3.975023e-02,"sim_inspiral:simulation_id:0",
         "process:process_id:0","GeneratePPNtwoPN",729617969,229059696,729617969,219374877,729617969,224062555,1.5339274926483630e+00,"MW",4.306241e-01,9.357402e-01,2.158344e-01,1.081501e-02,3.845842e+00,-6.440565e-02,6.349684e-01,5.513083e+00,1.473969e+00,2.235017e-02,2.562004e-02,"sim_inspiral:simulation_id:0",
         "process:process_id:0","GeneratePPNtwoPN",729681863,206630230,729681863,202848793,729681863,211456699,1.9330847913399339e+01,"MW",7.515846e-01,6.577424e-01,2.488916e-01,3.028014e-02,1.601627e+00,6.076538e-02,2.303801e+00,1.566367e+00,3.101873e+00,1.488195e-01,1.283618e-01,"sim_inspiral:simulation_id:0",
         "process:process_id:0","GeneratePPNtwoPN",729694144,284154654,729694144,264386547,729694144,270061246,2.2751598474503393e+01,"MW",7.468468e-01,3.277730e-01,2.119801e-01,1.874431e-02,3.322169e+00,8.275794e-01,1.091110e+00,4.199395e+00,8.930324e-01,3.666866e-02,5.064291e-02,"sim_inspiral:simulation_id:0",
         "process:process_id:0","GeneratePPNtwoPN",729764536,70862293,729764536,81858858,729764536,88375797,1.8358407657845980e+01,"MW",6.147531e-01,2.672280e-01,2.111855e-01,1.632345e-02,6.483063e+00,6.111837e-02,1.797555e+00,5.670452e+00,6.639351e-01,5.606090e-02,4.776958e-02,"sim_inspiral:simulation_id:0",
         "process:process_id:0","GeneratePPNtwoPN",730038491,224134445,730038491,242614821,730038491,242786644,2.2665412551326057e+01,"MW",4.796075e-01,5.158616e-01,2.496684e-01,1.763096e-02,1.501563e+00,-9.864419e-01,7.865220e-01,1.757983e+00,1.404372e+00,2.689775e-02,2.715807e-02,"sim_inspiral:simulation_id:0",
         "process:process_id:0","GeneratePPNtwoPN",730044412,982262105,730044412,961372713,730044412,963205807,3.1484905714790029e-01,"MW",5.013850e-01,6.585735e-01,2.454091e-01,1.180067e-02,4.242849e+00,6.282578e-01,7.867521e-01,2.708819e+00,3.952779e+00,1.606221e-02,1.764003e-02,"sim_inspiral:simulation_id:0",
         "process:process_id:0","GeneratePPNtwoPN",730095592,46397209,730095592,31506168,730095592,31765049,1.4570178974337049e+01,"MW",5.559129e-01,9.624907e-01,2.320753e-01,3.415684e-02,1.556809e+00,2.831370e-02,2.411938e+00,6.603464e-01,5.402467e-01,6.367563e-02,6.226464e-02,"sim_inspiral:simulation_id:0",
         "process:process_id:0","GeneratePPNtwoPN",730102082,725096226,730102082,736204270,730102082,743258921,1.6378081647973094e+01,"MW",5.013887e-01,7.331302e-01,2.411905e-01,6.121926e-03,6.276048e+00,-1.604328e-01,1.227519e+00,3.708639e+00,6.147322e+00,2.294837e-02,1.436030e-02,"sim_inspiral:simulation_id:0",
         "process:process_id:0","GeneratePPNtwoPN",730108306,126691580,730108306,138526668,730108306,130273524,1.8111537391915917e+01,"MW",9.915013e-01,7.893233e-01,2.467777e-01,1.782368e-02,3.987104e+00,-1.075616e+00,2.449116e+00,3.496756e+00,4.287682e+00,3.488884e-02,4.418639e-02,"sim_inspiral:simulation_id:0",
         "process:process_id:0","GeneratePPNtwoPN",730280559,594951153,730280559,582213685,730280559,577403682,1.8090727015506062e+01,"MW",4.635069e-01,2.348272e-01,2.231918e-01,1.228540e-02,3.029996e+00,-5.781979e-02,2.548772e+00,4.875161e+00,5.455772e+00,2.185589e-02,1.779139e-02,"sim_inspiral:simulation_id:0",
         "process:process_id:0","GeneratePPNtwoPN",730293268,223155022,730293268,203740310,730293268,202171270,2.1630566822000677e+01,"MW",2.062976e-01,7.026603e-01,1.754495e-01,4.996804e-02,3.904935e+00,4.787884e-01,1.993834e+00,3.222863e+00,2.448149e+00,9.999125e-02,9.460290e-02,"sim_inspiral:simulation_id:0",
         "process:process_id:0","GeneratePPNtwoPN",730439496,101240396,730439496,86972790,730439496,85477113,1.4360632583221628e+01,"MW",3.363041e-01,1.270488e-01,1.990119e-01,3.453983e-02,3.030954e+00,9.438003e-01,3.963962e-01,4.937902e+00,3.037810e+00,5.154045e-02,4.982929e-02,"sim_inspiral:simulation_id:0",
         "process:process_id:0","GeneratePPNtwoPN",730471588,462875366,730471588,454237697,730471588,446424859,2.3299584698089294e+01,"MW",4.678281e-01,4.542014e-01,2.499454e-01,4.406157e-02,4.860629e+00,-7.076663e-02,7.032911e-01,4.666312e+00,7.645742e-01,1.087873e-01,7.243074e-02,"sim_inspiral:simulation_id:0",
         "process:process_id:0","GeneratePPNtwoPN",730522179,805249155,730522179,812932109,730522179,803522558,1.3391211608271632e+01,"MW",3.775492e-01,5.633505e-01,2.402512e-01,6.564335e-03,3.182302e+00,-3.366536e-01,2.041870e+00,2.997374e+00,2.800705e+00,3.122883e-02,1.399725e-01,"sim_inspiral:simulation_id:0",
         "process:process_id:0","GeneratePPNtwoPN",730554388,838251114,730554388,839651299,730554388,843967390,2.2362661173293986e+01,"MW",8.237512e-01,3.413163e-01,2.071338e-01,1.514585e-02,2.654514e+00,-4.821524e-01,1.928607e+00,5.580217e-01,5.026746e+00,6.229409e-02,8.127336e-02,"sim_inspiral:simulation_id:0",
         "process:process_id:0","GeneratePPNtwoPN",730611443,860927701,730611443,864936729,730611443,860906941,1.4254670655814310e+01,"MW",2.191425e-01,7.021966e-01,1.812785e-01,3.761576e-02,3.917886e+00,3.277013e-01,1.863967e+00,1.129435e-01,9.940643e-01,1.374259e-01,1.824720e-01,"sim_inspiral:simulation_id:0",
         "process:process_id:0","GeneratePPNtwoPN",730617685,890367713,730617685,901360651,730617685,893704402,1.5993314983890288e+01,"MW",5.158386e-01,8.443427e-01,2.354176e-01,2.213793e-02,3.167887e+00,-1.141644e+00,2.770376e+00,1.328957e-01,2.831684e+00,3.817369e-02,4.679398e-02,"sim_inspiral:simulation_id:0",
         "process:process_id:0","GeneratePPNtwoPN",730624430,178919315,730624430,158476597,730624430,158145186,1.7871857693526479e+01,"MW",2.484307e-01,6.632002e-01,1.982494e-01,4.422310e-02,2.948693e+00,7.082207e-01,2.066029e+00,2.454964e+00,2.779745e+00,7.501096e-02,7.384384e-02,"sim_inspiral:simulation_id:0",
         "process:process_id:0","GeneratePPNtwoPN",730630941,93991280,730630941,75672777,730630941,76398589,1.9685396963531772e+01,"MW",4.213025e-01,5.685559e-01,2.444675e-01,9.898278e-03,3.871814e+00,1.093568e+00,1.085344e+00,5.665041e+00,5.352234e+00,2.327863e-02,2.533593e-02,"sim_inspiral:simulation_id:0",
         "process:process_id:0","GeneratePPNtwoPN",730694671,912394047,730694671,908583434,730694671,918452433,1.3436871306978993e+01,"MW",7.814615e-01,4.804512e-01,2.357753e-01,1.532150e-02,6.068737e+00,3.240695e-01,1.941548e+00,2.991142e-01,4.109507e+00,1.371430e-01,1.355937e-01,"sim_inspiral:simulation_id:0",
         "process:process_id:0","GeneratePPNtwoPN",730796622,80665112,730796622,68086759,730796622,64270036,1.7833898684539729e+01,"MW",3.509202e-01,9.477021e-01,1.972035e-01,4.488443e-02,2.810859e+00,-1.076374e-01,1.416414e+00,2.855884e+00,1.588485e+00,2.448113e-01,1.526982e-01,"sim_inspiral:simulation_id:0",
         "process:process_id:0","GeneratePPNtwoPN",730802600,998944521,730802601,11686911,730802601,3096836,1.9499256479206185e+01,"MW",9.134098e-01,5.554671e-01,2.351544e-01,1.138329e-02,4.561344e+00,-1.008147e+00,1.980811e+00,4.778016e+00,4.384748e+00,4.206584e-02,5.442391e-02,"sim_inspiral:simulation_id:0",
         "process:process_id:0","GeneratePPNtwoPN",730866431,387401104,730866431,398839696,730866431,405656310,1.3278464884530338e+01,"MW",4.837127e-01,2.842992e-01,2.331456e-01,3.191017e-02,5.290837e+00,-5.080627e-02,1.291741e+00,2.262630e+00,2.972454e+00,1.385203e-01,8.735820e-02,"sim_inspiral:simulation_id:0",
         "process:process_id:0","GeneratePPNtwoPN",730892176,366084099,730892176,376872603,730892176,372241166,2.0449427679466705e+01,"MW",1.725809e-01,3.740999e-01,2.160293e-01,2.424359e-02,3.199095e+00,-1.295645e+00,1.175338e+00,4.846408e+00,2.705982e+00,1.002556e-01,1.172625e-01,"sim_inspiral:simulation_id:0",
         "process:process_id:0","GeneratePPNtwoPN",731140485,911725044,731140485,920272951,731140485,928223603,1.7613148423901034e+01,"MW",7.714176e-01,8.162844e-01,2.498003e-01,2.634592e-02,4.039693e-01,-5.585201e-02,2.192795e+00,2.167985e+00,4.409524e+00,9.861054e-02,5.490194e-02,"sim_inspiral:simulation_id:0",
         "process:process_id:0","GeneratePPNtwoPN",731172240,184400558,731172240,174728399,731172240,178911525,2.4579298194704786e+00,"MW",6.166812e-01,5.574129e-01,2.493629e-01,4.006891e-02,1.493393e+00,1.230632e+00,1.007715e+00,2.427785e+00,4.815915e+00,1.586520e-01,2.046609e-01,"sim_inspiral:simulation_id:0",
         "process:process_id:0","GeneratePPNtwoPN",731185159,813154221,731185159,812896885,731185159,819461810,6.0565413496726093e+00,"MW",7.064097e-01,8.529835e-01,2.477913e-01,4.823419e-02,4.510478e+00,-2.564982e-01,2.470090e+00,1.664528e-01,4.789318e+00,1.383631e-01,1.174506e-01,"sim_inspiral:simulation_id:0",
         "process:process_id:0","GeneratePPNtwoPN",731197460,277676463,731197460,291418055,731197460,292910583,9.4826919273659591e+00,"MW",3.711900e-01,2.331999e-01,2.369683e-01,4.284752e-02,3.518734e+00,5.948118e-02,6.540372e-01,5.469215e+00,2.034424e+00,8.129788e-02,7.203316e-02,"sim_inspiral:simulation_id:0",
         "process:process_id:0","GeneratePPNtwoPN",731229381,555011749,731229381,542961465,731229381,537570566,1.8373990503379868e+01,"MW",4.727920e-01,7.147023e-01,2.396251e-01,5.182245e-02,3.929640e+00,5.059673e-01,1.297766e+00,6.493379e-01,9.071378e-01,3.080286e-01,2.242706e-01,"sim_inspiral:simulation_id:0",
         "process:process_id:0","GeneratePPNtwoPN",731242539,938991547,731242539,956631011,731242539,949265571,2.2039104517805907e+01,"MW",2.731761e-01,6.550263e-01,2.076902e-01,2.649396e-02,5.934820e+00,-8.598545e-01,1.367999e+00,5.790352e-01,3.955211e+00,9.674293e-02,1.696987e-01,"sim_inspiral:simulation_id:0",
         "process:process_id:0","GeneratePPNtwoPN",731318461,634250164,731318461,633358557,731318461,631345598,1.9186205078247522e+01,"MW",8.957789e-01,7.918277e-01,2.490515e-01,3.675682e-02,2.641808e+00,-6.981305e-01,2.752642e+00,1.167369e+00,5.872497e+00,5.038699e-01,2.302915e-01,"sim_inspiral:simulation_id:0",
         "process:process_id:0","GeneratePPNtwoPN",731388846,776893616,731388846,795371806,731388846,788636483,1.4791163625232876e+01,"MW",2.368531e-01,7.230675e-01,1.858606e-01,4.648903e-02,4.136102e+00,-9.884415e-01,1.502379e+00,3.923645e+00,1.154340e+00,1.082127e-01,1.619816e-01,"sim_inspiral:simulation_id:0",
         "process:process_id:0","GeneratePPNtwoPN",731739274,318018436,731739274,331925838,731739274,327011506,1.6398658055141567e+01,"MW",2.956036e-01,2.354508e-01,2.467925e-01,3.521717e-02,4.694480e+00,-1.583241e-01,1.633783e+00,5.642298e+00,5.311231e+00,1.308055e-01,1.276033e-01,"sim_inspiral:simulation_id:0",
         "process:process_id:0","GeneratePPNtwoPN",732000162,906048775,732000162,902619581,732000162,900417115,1.7066123991302319e+01,"MW",3.410049e-01,8.649936e-01,2.028056e-01,2.407701e-02,4.535572e+00,6.827114e-01,2.604668e+00,7.489803e-02,4.140161e+00,5.920897e-02,6.140964e-02,"sim_inspiral:simulation_id:0",
         "process:process_id:0","GeneratePPNtwoPN",732185095,355895042,732185095,370591116,732185095,361949493,2.0576895687857437e+01,"MW",4.591743e-01,6.638322e-01,2.416970e-01,3.156492e-02,5.224461e+00,-8.252054e-01,9.305724e-02,4.522573e+00,6.109436e+00,4.455877e-02,8.007148e-02,"sim_inspiral:simulation_id:0",
         "process:process_id:0","GeneratePPNtwoPN",732261635,485797405,732261635,500898228,732261635,505157858,1.7896253982691302e+01,"MW",9.087284e-01,5.546378e-01,2.353626e-01,4.836494e-02,4.584373e-01,-5.851666e-01,1.759637e+00,3.483509e+00,4.486299e+00,1.361360e-01,1.159283e-01,"sim_inspiral:simulation_id:0",
         "process:process_id:0","GeneratePPNtwoPN",732287093,601689816,732287093,607738848,732287093,602140573,9.8731449379689162e-01,"MW",5.732832e-01,2.358972e-01,2.065386e-01,3.838006e-02,3.598143e-01,1.517913e-01,9.897546e-01,2.193654e-01,3.541633e+00,1.259224e-01,1.229416e-01,"sim_inspiral:simulation_id:0",
         "process:process_id:0","GeneratePPNtwoPN",732293043,227949023,732293043,246338739,732293043,246320922,2.6445133399632241e+00,"MW",7.600861e-01,7.666690e-01,2.499953e-01,2.628847e-02,2.557770e+00,-1.013099e+00,6.092623e-01,2.124619e+00,1.654593e+00,3.593197e-02,3.629445e-02,"sim_inspiral:simulation_id:0",
         "process:process_id:0","GeneratePPNtwoPN",732305739,183656864,732305739,176484918,732305739,185191050,6.1808233551308511e+00,"MW",1.695913e-01,4.250362e-01,2.038635e-01,4.769718e-02,4.546051e+00,1.913032e-01,2.610644e+00,5.053370e+00,4.448801e+00,1.397114e-01,2.551970e-01,"sim_inspiral:simulation_id:0",
         "process:process_id:0","GeneratePPNtwoPN",732344364,807096004,732344364,801522548,732344364,807642886,1.6939539160521495e+01,"MW",2.690505e-01,4.693204e-01,2.316083e-01,4.117026e-02,1.326420e+00,-1.302390e-01,1.393904e+00,2.986825e+00,4.183467e+00,2.267811e-01,1.696998e-01,"sim_inspiral:simulation_id:0",
         "process:process_id:0","GeneratePPNtwoPN",732357018,268912315,732357018,275114155,732357018,283371780,2.0464013025967610e+01,"MW",3.917628e-01,6.128584e-01,2.378913e-01,4.062142e-02,9.553824e-01,2.309192e-01,1.499603e+00,2.637737e+00,1.923332e-01,1.799288e-01,1.123166e-01,"sim_inspiral:simulation_id:0",
         "process:process_id:0","GeneratePPNtwoPN",732376103,20349026,732376103,36721750,732376103,28913432,1.7798473817523983e+00,"MW",7.870417e-01,3.997393e-01,2.233744e-01,2.279115e-02,4.050372e-01,-9.975489e-01,1.292241e+00,4.104519e+00,6.840099e-01,1.006995e-01,1.316129e-01,"sim_inspiral:simulation_id:0",
         "process:process_id:0","GeneratePPNtwoPN",732388552,950219840,732388552,946290629,732388552,947080031,5.2476297916140817e+00,"MW",9.712697e-01,9.726200e-01,2.499999e-01,5.565798e-02,5.030838e+00,-4.872659e-01,1.190315e+00,2.694115e+00,1.370811e+00,4.351422e-01,3.009517e-01,"sim_inspiral:simulation_id:0",
         "process:process_id:0","GeneratePPNtwoPN",732427068,914163589,732427068,932664568,732427068,932999336,1.5975801221550340e+01,"MW",6.514471e-01,6.098349e-01,2.497279e-01,3.103810e-02,6.029729e+00,-9.661842e-01,1.224639e+00,8.926761e-01,1.571124e+00,6.324445e-02,6.360831e-02,"sim_inspiral:simulation_id:0",
         "process:process_id:0","GeneratePPNtwoPN",732446208,594844818,732446208,600230272,732446208,607431181,2.1306935501082076e+01,"MW",9.729813e-01,6.392699e-01,2.392893e-01,3.936031e-02,9.133376e-01,4.047986e-01,8.495023e-01,5.510831e+00,1.853536e+00,1.054972e-01,8.339956e-02,"sim_inspiral:simulation_id:0",
         "process:process_id:0","GeneratePPNtwoPN",732471402,448069930,732471402,427834231,732471402,427119742,4.3243887496284312e+00,"MW",5.253254e-01,8.391819e-01,2.367733e-01,1.718291e-02,5.659867e+00,6.220115e-01,2.887948e+00,5.694706e+00,4.114469e-01,1.863315e-02,1.800627e-02,"sim_inspiral:simulation_id:0",
         "process:process_id:0","GeneratePPNtwoPN",732490712,171853065,732490712,188282988,732490712,191984537,9.7028865445860557e+00,"MW",4.356202e-01,7.969264e-01,2.285175e-01,1.042110e-02,4.475987e+00,-6.037731e-01,1.615462e+00,4.526645e+00,3.581446e+00,3.929542e-02,2.795713e-02,"sim_inspiral:simulation_id:0",
         "process:process_id:0","GeneratePPNtwoPN",732516215,870939970,732516215,882370042,732516215,884784520,1.6806643738994996e+01,"MW",5.529197e-01,4.483595e-01,2.472738e-01,1.626740e-02,5.474009e+00,1.949681e-01,1.274468e+00,5.326100e+00,4.025655e+00,6.173827e-02,6.243953e-02,"sim_inspiral:simulation_id:0",
         "process:process_id:0","GeneratePPNtwoPN",732522538,918012857,732522538,935817355,732522538,938202472,1.8567854568155276e+01,"MW",3.639697e-01,7.003057e-01,2.250323e-01,4.300519e-02,6.201872e+00,-2.813781e-01,2.019425e+00,4.413550e-01,1.729855e+00,9.310905e-02,8.024418e-02,"sim_inspiral:simulation_id:0",
         "process:process_id:0","GeneratePPNtwoPN",732535252,845725298,732535252,857225562,732535252,863811600,2.2109170490801333e+01,"MW",8.206142e-01,8.762636e-01,2.497311e-01,2.121545e-02,1.616975e+00,-3.032157e-01,5.969019e-01,3.642030e+00,4.999246e-01,4.717001e-02,2.987683e-02,"sim_inspiral:simulation_id:0",
         "process:process_id:0","GeneratePPNtwoPN",732592716,902478218,732592716,897702821,732592716,907620128,1.4115111631676555e+01,"MW",5.927691e-01,2.440923e-01,2.066011e-01,1.188520e-02,6.264670e+00,3.722880e-01,8.774558e-01,9.389287e-01,2.557840e+00,6.553425e-02,6.690960e-02,"sim_inspiral:simulation_id:0",
         "process:process_id:0","GeneratePPNtwoPN",732611776,741736412,732611776,751448105,732611776,756149765,1.9424007008845606e+01,"MW",2.864898e-01,8.226762e-01,1.915777e-01,2.107999e-02,6.404330e+00,2.627160e-01,1.091718e+00,1.394951e+00,2.148638e+00,6.400432e-02,5.355408e-02,"sim_inspiral:simulation_id:0",
         "process:process_id:0","GeneratePPNtwoPN",732694401,758935928,732694401,747582757,732694401,745497262,1.8438239526777632e+01,"MW",7.840965e-01,4.388528e-01,2.300761e-01,2.201504e-02,2.719355e+00,-1.991425e-01,1.264434e+00,1.296293e+00,5.148216e+00,1.081110e-01,1.108880e-01,"sim_inspiral:simulation_id:0",
         "process:process_id:0","GeneratePPNtwoPN",732771341,65268993,732771341,73993676,732771341,64763070,1.5868783738062614e+01,"MW",1.876705e-01,2.180077e-01,2.486019e-01,3.949521e-02,3.336233e+00,-8.578853e-01,6.329632e-01,7.735326e-01,1.363628e+00,8.492792e-02,1.022178e-01,"sim_inspiral:simulation_id:0",
         "process:process_id:0","GeneratePPNtwoPN",732777167,38652778,732777167,58293273,732777167,52753643,1.7491540509056716e+01,"MW",6.045269e-01,5.341086e-01,2.490438e-01,1.984472e-02,5.117707e+00,-1.053946e+00,7.643663e-01,2.322644e+00,3.047455e+00,2.891948e-02,3.788399e-02,"sim_inspiral:simulation_id:0",
         "process:process_id:0","GeneratePPNtwoPN",732783775,672955990,732783775,670153972,732783775,661925066,1.9332298320937486e+01,"MW",2.887973e-01,2.171686e-01,2.449896e-01,1.214271e-02,4.484602e+00,1.228153e-01,2.077820e+00,8.041784e-01,3.001753e+00,1.070956e-01,3.694211e-02,"sim_inspiral:simulation_id:0",
         "process:process_id:0","GeneratePPNtwoPN",732866719,100587845,732866719,110309080,732866719,112428620,1.8435220328296225e+01,"MW",8.091214e-01,5.032928e-01,2.364246e-01,1.544242e-02,1.354285e+00,-8.462494e-01,2.670444e+00,3.003259e+00,3.784377e+00,2.877125e-02,2.843301e-02,"sim_inspiral:simulation_id:0",
         "process:process_id:0","GeneratePPNtwoPN",733032458,306789875,733032458,310426886,733032458,308498903,1.6599938426899413e+01,"MW",3.954599e-01,3.512926e-01,2.491254e-01,4.854441e-02,4.730986e+00,4.516911e-01,1.401496e+00,5.661290e+00,6.015934e+00,2.726154e-01,6.075038e-01,"sim_inspiral:simulation_id:0",
         "process:process_id:0","GeneratePPNtwoPN",733057696,66337109,733057696,55525750,733057696,55789352,2.3629621273101204e+01,"MW",3.797382e-01,8.101791e-01,2.172860e-01,5.832478e-03,3.810268e+00,-1.956062e-01,1.338904e+00,3.083914e+00,1.057085e+00,2.361067e-02,1.916128e-02,"sim_inspiral:simulation_id:0",
         "process:process_id:0","GeneratePPNtwoPN",733115110,475383282,733115110,493887586,733115110,495424289,1.5621733619508644e+01,"MW",4.485740e-01,1.499475e-01,1.877647e-01,9.903096e-03,5.350619e+00,-3.226570e-01,2.544020e+00,1.851977e+00,2.677980e+00,1.363495e-02,1.268370e-02,"sim_inspiral:simulation_id:0",
         "process:process_id:0","GeneratePPNtwoPN",733127587,649700522,733127587,657046609,733127587,648077150,1.9097104658231967e+01,"MW",8.342950e-01,7.357751e-01,2.490157e-01,3.327589e-02,4.009928e+00,-8.673058e-01,1.339425e+00,9.242831e-01,4.572278e+00,2.041050e-01,1.566535e-01,"sim_inspiral:simulation_id:0",
         "process:process_id:0","GeneratePPNtwoPN",733210840,902934551,733210840,917248607,733210840,910436062,1.8286324963399935e+01,"MW",3.449783e-01,9.641837e-01,1.940728e-01,4.167447e-02,4.155939e+00,-1.298465e+00,2.078900e+00,3.484815e+00,3.043309e+00,1.188988e-01,1.519339e-01,"sim_inspiral:simulation_id:0",
         "process:process_id:0","GeneratePPNtwoPN",733217213,265817642,733217213,283752476,733217213,276940609,2.0061272122446034e+01,"MW",1.755837e-01,9.172833e-01,1.348507e-01,5.359679e-02,5.428520e+00,-1.082698e+00,2.954146e+00,6.223424e+00,6.059561e-01,6.363167e-02,8.922315e-02,"sim_inspiral:simulation_id:0",
         "process:process_id:0","GeneratePPNtwoPN",733299692,216977358,733299692,202176131,733299692,197611314,1.9034819654019344e+01,"MW",2.032103e-01,2.153112e-01,2.497910e-01,3.669282e-02,3.895099e+00,5.470381e-01,1.810345e+00,5.717777e+00,2.887278e+00,1.145187e-01,8.125617e-02,"sim_inspiral:simulation_id:0",
         "process:process_id:0","GeneratePPNtwoPN",733306048,679403543,733306048,681404281,733306048,690875307,2.0805337949113714e+01,"MW",3.183472e-01,2.044873e-01,2.381436e-01,6.139769e-03,1.402086e+00,2.259747e-01,1.408982e+00,3.544266e+00,8.911830e-01,5.309348e-02,5.292035e-02,"sim_inspiral:simulation_id:0",
         "process:process_id:0","GeneratePPNtwoPN",733382739,41209698,733382739,53179829,733382739,45265972,1.8166541570557488e+01,"MW",3.461804e-01,7.605086e-01,2.149589e-01,2.866363e-03,4.781599e+00,-3.192374e-01,1.212029e+00,6.245181e+00,3.988579e+00,9.844466e-03,1.830861e-02,"sim_inspiral:simulation_id:0",
         "process:process_id:0","GeneratePPNtwoPN",733389151,822371960,733389151,803299909,733389151,801370780,1.9952746782398059e+01,"MW",6.553162e-01,4.064179e-01,2.362611e-01,3.102577e-02,3.730227e+00,6.664303e-01,1.315122e+00,4.572027e+00,2.942018e-01,9.926080e-02,9.538170e-02,"sim_inspiral:simulation_id:0",
         "process:process_id:0","GeneratePPNtwoPN",733395143,339416265,733395143,356844929,733395143,352021365,2.1621613815728988e+01,"MW",6.788684e-01,3.725627e-01,2.287828e-01,1.257660e-02,6.357441e+00,-1.402584e+00,5.826091e-01,1.119002e+00,4.872292e+00,1.821697e-02,2.245089e-02,"sim_inspiral:simulation_id:0",
         "process:process_id:0","GeneratePPNtwoPN",733401777,296338558,733401777,310989041,733401777,313835473,2.3469424934631419e+01,"MW",8.511620e-01,6.685402e-01,2.463899e-01,4.604251e-02,2.119448e+00,-7.918617e-01,1.858765e+00,3.930456e+00,5.088939e+00,2.085268e-01,1.481819e-01,"sim_inspiral:simulation_id:0",
         "process:process_id:0","GeneratePPNtwoPN",733458718,388179570,733458718,404955202,733458718,409042505,1.5329700329287185e+01,"MW",8.665444e-01,3.351536e-01,2.011148e-01,5.396651e-02,5.662354e+00,-3.563197e-01,1.533157e+00,2.317367e-01,4.858935e-01,1.452479e-01,1.209128e-01,"sim_inspiral:simulation_id:0",
         "process:process_id:0","GeneratePPNtwoPN",733471495,769623697,733471495,774879815,733471495,768442859,1.8888690535173648e+01,"MW",8.723820e-01,6.626264e-01,2.453319e-01,4.822979e-02,3.260711e+00,-9.823326e-01,2.304878e+00,1.527582e+00,8.570524e-01,1.746852e-01,1.916598e-01,"sim_inspiral:simulation_id:0",
         "process:process_id:0","GeneratePPNtwoPN",733490608,896109343,733490608,883366655,733490608,889924358,2.1242845523688528e-01,"MW",8.387362e-01,4.267471e-01,2.235029e-01,3.881315e-02,3.400696e+00,2.184882e-01,2.772674e+00,3.149665e+00,3.462029e+00,6.242412e-02,9.554336e-02,"sim_inspiral:simulation_id:0",
         "process:process_id:0","GeneratePPNtwoPN",733497159,759752035,733497159,773113091,733497159,767829581,2.0370949200954702e+00,"MW",9.374716e-01,9.676279e-01,2.499373e-01,6.253708e-03,8.832645e-01,-1.525934e-01,1.593171e+00,1.240914e+00,4.669905e+00,3.860851e-02,2.219152e-01,"sim_inspiral:simulation_id:0",
         "process:process_id:0","GeneratePPNtwoPN",733548427,984352589,733548427,987464825,733548427,996702715,1.6317259460542765e+01,"MW",3.234316e-01,7.132527e-01,2.146510e-01,4.310340e-02,6.390487e+00,2.519613e-01,2.747698e+00,4.890750e+00,2.795573e+00,1.251415e-01,7.426751e-02,"sim_inspiral:simulation_id:0",
         "process:process_id:0","GeneratePPNtwoPN",733554578,713086128,733554578,719516444,733554578,710255606,1.8030473048430348e+01,"MW",4.541154e-01,1.663514e-01,1.962256e-01,1.310743e-02,4.391010e+00,-2.522729e-01,2.745529e+00,4.751210e-01,6.090056e+00,4.432883e-02,8.745790e-02,"sim_inspiral:simulation_id:0",
         "process:process_id:0","GeneratePPNtwoPN",733573872,557306767,733573872,547073766,733573872,553335673,2.3404547773181566e+01,"MW",9.275504e-01,3.279910e-01,1.929911e-01,5.400981e-03,1.447618e+00,1.227913e+00,1.757587e+00,4.205750e-01,5.392000e+00,4.120959e-02,6.488635e-02,"sim_inspiral:simulation_id:0",
         "process:process_id:0","GeneratePPNtwoPN",733586675,266995907,733586675,264659319,733586675,260847352,2.9705928662088184e+00,"MW",9.818603e-01,7.770968e-01,2.466121e-01,2.036736e-02,4.962965e+00,-6.530619e-01,1.047029e+00,5.780869e+00,3.326927e+00,2.107354e-01,1.240547e-01,"sim_inspiral:simulation_id:0",
         "process:process_id:0","GeneratePPNtwoPN",733643584,746314764,733643584,745114120,733643584,738320937,1.8822062968028089e+01,"MW",6.375395e-01,6.982931e-01,2.494829e-01,2.860870e-02,3.286697e+00,-6.535859e-01,1.300271e+00,4.424186e+00,4.324495e+00,1.260642e-01,1.133192e-01,"sim_inspiral:simulation_id:0",
         "process:process_id:0","GeneratePPNtwoPN",733656310,875503302,733656310,859547940,733656310,865616169,2.2366777443033126e+01,"MW",9.532962e-01,6.410922e-01,2.404142e-01,4.544966e-02,3.055163e+00,3.780073e-01,1.820550e+00,9.263864e-01,5.370241e+00,1.134707e-01,1.674756e-01,"sim_inspiral:simulation_id:0",
         "process:process_id:0","GeneratePPNtwoPN",733663131,79047203,733663131,87598715,733663131,95535070,2.6646541568554111e-01,"MW",7.716151e-01,2.815649e-01,1.958727e-01,2.217382e-02,2.159559e+00,-6.770322e-02,1.945103e+00,5.229382e+00,4.185401e+00,1.381076e-01,7.554134e-02,"sim_inspiral:simulation_id:0",
         "process:process_id:0","GeneratePPNtwoPN",733675478,55496693,733675478,72184352,733675478,73669679,3.7055713444078964e+00,"MW",2.657188e-01,2.385439e-01,2.492740e-01,1.912859e-02,3.065005e+00,-9.072286e-01,8.639157e-01,1.629606e+00,5.804779e+00,3.411354e-02,3.296354e-02,"sim_inspiral:simulation_id:0",
         "process:process_id:0","GeneratePPNtwoPN",733720153,83793402,733720153,82496543,733720153,79624364,1.6149278140974541e+01,"MW",2.081247e-01,7.099386e-01,1.753070e-01,4.017993e-02,4.323865e+00,5.751702e-01,2.435956e+00,8.594210e-01,1.028518e+00,1.083167e-01,1.109213e-01,"sim_inspiral:simulation_id:0",
         "process:process_id:0","GeneratePPNtwoPN",734153175,166358232,734153175,173928382,734153175,172580511,1.6762516401161751e+01,"MW",9.350129e-01,8.796733e-01,2.497675e-01,1.297032e-02,4.953996e+00,3.139643e-01,1.262302e+00,2.468208e+00,1.351739e+00,7.064322e-02,8.792304e-02,"sim_inspiral:simulation_id:0",
         "process:process_id:0","GeneratePPNtwoPN",734159782,786992073,734159782,783859149,734159782,778004451,1.8602991877252030e+01,"MW",3.497006e-01,9.935093e-01,1.925664e-01,2.069838e-02,4.568431e+00,3.997076e-01,2.094409e+00,2.214814e+00,5.193686e+00,7.379127e-02,5.712751e-02,"sim_inspiral:simulation_id:0",
         "process:process_id:0","GeneratePPNtwoPN",734185204,258759499,734185204,268874948,734185204,276108573,1.6838456144597795e+00,"MW",6.365608e-01,8.807281e-01,2.435259e-01,2.714367e-02,2.260994e+00,3.227910e-02,7.828082e-01,3.224190e+00,2.777359e+00,6.613952e-02,4.576517e-02,"sim_inspiral:simulation_id:0",
         "process:process_id:0","GeneratePPNtwoPN",734217213,788791180,734217213,771476097,734217213,768087364,1.0599725950952205e+01,"MW",6.900985e-01,3.374195e-01,2.205476e-01,9.428775e-03,1.453034e+00,5.829964e-01,1.658293e+00,1.012255e+00,4.381511e+00,2.507986e-02,2.021451e-02,"sim_inspiral:simulation_id:0",
         "process:process_id:0","GeneratePPNtwoPN",734242263,833891332,734242263,853831270,734242263,854845970,1.7577123131404321e+01,"MW",7.229614e-01,8.809807e-01,2.475735e-01,4.693335e-02,5.963076e+00,-5.456882e-01,1.289041e+00,4.508798e+00,4.302352e+00,1.762175e-01,1.700960e-01,"sim_inspiral:simulation_id:0",
         "process:process_id:0","GeneratePPNtwoPN",734248811,175163269,734248811,194488809,734248811,196377467,1.9400808503482903e+01,"MW",7.415988e-01,4.736628e-01,2.378476e-01,2.609370e-02,2.798864e-01,-5.352574e-01,2.510020e+00,1.724999e+00,2.316287e+00,3.507172e-02,3.203247e-02,"sim_inspiral:simulation_id:0",
         "process:process_id:0","GeneratePPNtwoPN",734267901,177167177,734267901,162486193,734267901,157380612,7.1810537077486514e-01,"MW",7.555234e-01,7.706875e-01,2.499753e-01,3.726980e-02,4.956441e+00,1.620531e-01,1.241567e+00,5.541099e+00,1.442504e+00,9.871487e-02,7.475156e-02,"sim_inspiral:simulation_id:0",
         "process:process_id:0","GeneratePPNtwoPN",734274293,951875448,734274293,970662952,734274293,969107049,2.4987379975989459e+00,"MW",4.503347e-01,4.867440e-01,2.496226e-01,5.432899e-03,2.360839e+00,-1.149298e+00,1.918351e+00,3.567144e+00,2.278799e+00,1.667564e-02,1.627538e-02,"sim_inspiral:simulation_id:0",
         "process:process_id:0","GeneratePPNtwoPN",734287149,523487568,734287149,503753342,734287149,509225254,6.0795071699304710e+00,"MW",6.716217e-01,9.503666e-01,2.426166e-01,2.663983e-02,5.262978e+00,7.472122e-01,9.333202e-01,1.822442e+00,3.635704e+00,4.242907e-02,5.872633e-02,"sim_inspiral:simulation_id:0",
         "process:process_id:0","GeneratePPNtwoPN",734299899,278395653,734299899,291209735,734299899,283681374,9.6308023415298933e+00,"MW",6.634058e-01,6.945775e-01,2.498683e-01,1.945815e-02,2.616291e+00,-3.219282e-01,7.018972e-01,3.616798e+00,4.433297e+00,3.841944e-02,7.524493e-02,"sim_inspiral:simulation_id:0",
         "process:process_id:0","GeneratePPNtwoPN",734306023,134872794,734306023,140632952,734306023,146801774,1.1336530960392620e+01,"MW",6.773332e-01,6.714906e-01,2.499953e-01,2.038772e-02,5.625276e+00,-4.124268e-01,2.023530e+00,1.684140e+00,3.912430e+00,7.693520e-02,6.585871e-02,"sim_inspiral:simulation_id:0",
         "process:process_id:0","GeneratePPNtwoPN",734312407,476885796,734312407,485847740,734312407,488348842,1.3114814778471159e+01,"MW",6.116094e-01,5.321608e-01,2.487938e-01,8.517673e-03,4.453907e+00,3.272416e-01,2.862508e+00,3.217419e+00,4.629627e+00,2.062647e-02,1.622020e-02,"sim_inspiral:simulation_id:0",
         "process:process_id:0","GeneratePPNtwoPN",734344312,481071234,734344312,482779176,734344312,474867075,2.2001580673799747e+01,"MW",5.246214e-01,8.283209e-01,2.374029e-01,4.863238e-02,5.451063e+00,8.228447e-02,2.628639e+00,4.533159e+00,1.388760e+00,1.641296e-01,1.272696e-01,"sim_inspiral:simulation_id:0"
      </Stream>
   </Table>
   <Table Name="sngl_inspiralgroup:sngl_inspiral:table">
      <Column Name="sngl_inspiralgroup:sngl_inspiral:process_id" Type="ilwd:char"/>
      <Column Name="sngl_inspiralgroup:sngl_inspiral:ifo" Type="lstring"/>
      <Column Name="sngl_inspiralgroup:sngl_inspiral:search" Type="lstring"/>
      <Column Name="sngl_inspiralgroup:sngl_inspiral:channel" Type="lstring"/>
      <Column Name="sngl_inspiralgroup:sngl_inspiral:end_time" Type="int_4s"/>
      <Column Name="sngl_inspiralgroup:sngl_inspiral:end_time_ns" Type="int_4s"/>
      <Column Name="sngl_inspiralgroup:sngl_inspiral:end_time_gmst" Type="real_8"/>
      <Column Name="sngl_inspiralgroup:sngl_inspiral:impulse_time" Type="int_4s"/>
      <Column Name="sngl_inspiralgroup:sngl_inspiral:impulse_time_ns" Type="int_4s"/>
      <Column Name="sngl_inspiralgroup:sngl_inspiral:template_duration" Type="real_8"/>
      <Column Name="sngl_inspiralgroup:sngl_inspiral:event_duration" Type="real_8"/>
      <Column Name="sngl_inspiralgroup:sngl_inspiral:amplitude" Type="real_4"/>
      <Column Name="sngl_inspiralgroup:sngl_inspiral:eff_distance" Type="real_4"/>
      <Column Name="sngl_inspiralgroup:sngl_inspiral:coa_phase" Type="real_4"/>
      <Column Name="sngl_inspiralgroup:sngl_inspiral:mass1" Type="real_4"/>
      <Column Name="sngl_inspiralgroup:sngl_inspiral:mass2" Type="real_4"/>
      <Column Name="sngl_inspiralgroup:sngl_inspiral:mchirp" Type="real_4"/>
      <Column Name="sngl_inspiralgroup:sngl_inspiral:eta" Type="real_4"/>
      <Column Name="sngl_inspiralgroup:sngl_inspiral:tau0" Type="real_4"/>
      <Column Name="sngl_inspiralgroup:sngl_inspiral:tau2" Type="real_4"/>
      <Column Name="sngl_inspiralgroup:sngl_inspiral:tau3" Type="real_4"/>
      <Column Name="sngl_inspiralgroup:sngl_inspiral:tau4" Type="real_4"/>
      <Column Name="sngl_inspiralgroup:sngl_inspiral:tau5" Type="real_4"/>
      <Column Name="sngl_inspiralgroup:sngl_inspiral:ttotal" Type="real_4"/>
      <Column Name="sngl_inspiralgroup:sngl_inspiral:psi0" Type="real_4"/>
      <Column Name="sngl_inspiralgroup:sngl_inspiral:psi3" Type="real_4"/>
      <Column Name="sngl_inspiralgroup:sngl_inspiral:f_final" Type="real_4"/>
      <Column Name="sngl_inspiralgroup:sngl_inspiral:snr" Type="real_4"/>
      <Column Name="sngl_inspiralgroup:sngl_inspiral:chisq" Type="real_4"/>
      <Column Name="sngl_inspiralgroup:sngl_inspiral:chisq_dof" Type="int_4s"/>
      <Column Name="sngl_inspiralgroup:sngl_inspiral:sigmasq" Type="real_8"/>
      <Column Name="sngl_inspiralgroup:sngl_inspiral:alpha" Type="real_4"/>
      <Stream Name="sngl_inspiralgroup:sngl_inspiral:table" Type="Local" Delimiter=",">
         "process:process_id:0","H1","FindChirpSPtwoPN","LSC-AS_Q",729337420,595458984,1.9390385748822656e+01,729337420,595458984,1.3171710968017578e+01,1.4648437500000000e-03,0.000000e+00,1.145837e-01,5.977207e-01,4.737680e-01,4.737679e-01,4.124390e-01,2.500000e-01,1.314160e+01,6.555465e-01,3.874122e-01,2.024626e-02,0.000000e+00,1.342998e+01,0.000000e+00,0.000000e+00,0.000000e+00,1.598958e+01,3.523050e+01,15,3.3567536318617415e+00,0.000000e+00,
         "process:process_id:0","H1","FindChirpSPtwoPN","LSC-AS_Q",729344213,961181640,2.1282598345192770e+01,729344213,961181640,8.6134786605834961e+00,1.2207031250000000e-03,0.000000e+00,4.215213e-02,2.439633e+00,6.096935e-01,6.096934e-01,5.307690e-01,2.500000e-01,8.631215e+00,5.093985e-01,3.274483e-01,1.861357e-02,0.000000e+00,8.831779e+00,0.000000e+00,0.000000e+00,0.000000e+00,5.224211e+01,4.161874e+01,15,4.8493149589288267e+00,0.000000e+00,
         "process:process_id:0","H1","FindChirpSPtwoPN","LSC-AS_Q",729388704,735839843,9.6749834453024803e+00,729388704,735839843,6.1178612709045410e+00,1.4648437500000000e-03,0.000000e+00,2.012784e-01,-1.679914e+00,7.463689e-01,7.463688e-01,6.497518e-01,2.500000e-01,6.161247e+00,4.161172e-01,2.861419e-01,1.739999e-02,0.000000e+00,6.308622e+00,0.000000e+00,0.000000e+00,0.000000e+00,1.389435e+01,1.525034e+01,15,7.8211550331075648e+00,0.000000e+00,
         "process:process_id:0","H1","FindChirpSPtwoPN","LSC-AS_Q",729413808,105224609,1.6667233478600782e+01,729413808,105224609,5.3153672218322754e+00,1.2207031250000000e-03,0.000000e+00,9.822398e-02,-4.080433e-01,8.108323e-01,8.108323e-01,7.058705e-01,2.500000e-01,5.366685e+00,3.830347e-01,2.707674e-01,1.692608e-02,0.000000e+00,5.495878e+00,0.000000e+00,0.000000e+00,0.000000e+00,3.169676e+01,3.451105e+01,15,9.6931459181824433e+00,0.000000e+00,
         "process:process_id:0","H1","FindChirpSPtwoPN","LSC-AS_Q",729433362,284423828,2.2113821467960047e+01,729433362,284423828,5.0788516998291016e+00,1.2207031250000000e-03,0.000000e+00,6.918791e-02,-6.582500e-01,8.328362e-01,8.328361e-01,7.250260e-01,2.500000e-01,5.132456e+00,3.729148e-01,2.659770e-01,1.677569e-02,0.000000e+00,5.256170e+00,0.000000e+00,0.000000e+00,0.000000e+00,4.516621e+01,3.967292e+01,15,9.7653483408465203e+00,0.000000e+00,
         "process:process_id:0","H1","FindChirpSPtwoPN","LSC-AS_Q",729452123,231933593,3.3394640510694846e+00,729452123,231933593,8.5696287155151367e+00,9.7656250000000000e-04,0.000000e+00,3.000088e-01,-2.179559e+00,6.115401e-01,6.115401e-01,5.323766e-01,2.500000e-01,8.587819e+00,5.078602e-01,3.267888e-01,1.859481e-02,0.000000e+00,8.787486e+00,0.000000e+00,0.000000e+00,0.000000e+00,8.347820e+00,3.858637e+01,15,6.2721171763012524e+00,0.000000e+00,
         "process:process_id:0","H1","FindChirpSPtwoPN","LSC-AS_Q",729541543,751220703,4.2465042064752847e+00,729541543,751220703,5.1167211532592773e+00,1.4648437500000000e-03,0.000000e+00,5.005838e-02,-3.111963e+00,8.292058e-01,8.292058e-01,7.218656e-01,2.500000e-01,5.169961e+00,3.745475e-01,2.667527e-01,1.680013e-02,0.000000e+00,5.294556e+00,0.000000e+00,0.000000e+00,0.000000e+00,6.432123e+01,1.706600e+02,15,1.0367218144758347e+01,0.000000e+00,
         "process:process_id:0","H1","FindChirpSPtwoPN","LSC-AS_Q",729554016,981689453,7.7207767198276187e+00,729554016,981689453,1.9551969528198242e+01,1.7089843750000000e-03,0.000000e+00,9.591941e-02,3.680461e-01,6.917464e-01,2.148039e-01,3.248740e-01,1.808028e-01,1.956093e+01,8.852257e-01,5.517097e-01,2.533637e-02,0.000000e+00,1.991978e+01,0.000000e+00,0.000000e+00,0.000000e+00,1.782843e+01,3.158001e+01,15,2.9244160081479662e+00,0.000000e+00,
         "process:process_id:0","H1","FindChirpSPtwoPN","LSC-AS_Q",729592706,395507812,1.8497260584193800e+01,729592706,395507812,4.2132863998413086e+00,1.4648437500000000e-03,0.000000e+00,3.576562e-02,-1.260069e+00,9.293830e-01,9.293829e-01,8.090749e-01,2.500000e-01,4.274972e+00,3.341754e-01,2.472221e-01,1.617342e-02,0.000000e+00,4.378099e+00,0.000000e+00,0.000000e+00,0.000000e+00,1.069844e+02,2.457687e+02,15,1.4641050635831197e+01,0.000000e+00,
         "process:process_id:0","H1","FindChirpSPtwoPN","LSC-AS_Q",729617969,220458984,1.5339251056727436e+00,729617969,220458984,8.2174539566040039e+00,1.2207031250000000e-03,0.000000e+00,2.274345e-02,1.769843e+00,7.926223e-01,5.002189e-01,5.452891e-01,2.372116e-01,8.251569e+00,5.002153e-01,3.319028e-01,1.884067e-02,0.000000e+00,8.438722e+00,0.000000e+00,0.000000e+00,0.000000e+00,1.323160e+02,4.254803e+02,15,9.0560190727898604e+00,0.000000e+00,
         "process:process_id:0","H1","FindChirpSPtwoPN","LSC-AS_Q",729681863,203125000,1.9330846938437059e+01,729681863,203125000,6.7724876403808594e+00,1.4648437500000000e-03,0.000000e+00,1.516394e-01,-3.035946e+00,7.029023e-01,7.029023e-01,6.119120e-01,2.500000e-01,6.809254e+00,4.418493e-01,2.978199e-01,1.775150e-02,0.000000e+00,6.971035e+00,0.000000e+00,0.000000e+00,0.000000e+00,2.214977e+01,1.503850e+01,15,1.1281397612602483e+01,0.000000e+00,
         "process:process_id:0","H1","FindChirpSPtwoPN","LSC-AS_Q",729694144,263916015,2.2751592837650744e+01,729694144,263916015,1.2535630226135254e+01,1.4648437500000000e-03,0.000000e+00,3.748093e-02,-2.191103e-01,8.135887e-01,3.046449e-01,4.234604e-01,1.982138e-01,1.257650e+01,6.661852e-01,4.375439e-01,2.218714e-02,0.000000e+00,1.282733e+01,0.000000e+00,0.000000e+00,0.000000e+00,6.554545e+01,7.289645e+01,15,6.0353969358659905e+00,0.000000e+00,
         "process:process_id:0","H1","FindChirpSPtwoPN","LSC-AS_Q",729764536,81542968,1.8358410627560485e+01,729764536,81542968,1.7549753189086914e+01,1.4648437500000000e-03,0.000000e+00,5.795445e-02,-1.059260e+00,6.507987e-01,2.545180e-01,3.468479e-01,2.020990e-01,1.753946e+01,8.101712e-01,4.940216e-01,2.349963e-02,0.000000e+00,1.787911e+01,0.000000e+00,0.000000e+00,0.000000e+00,3.295031e+01,3.581916e+01,15,3.6466364335389678e+00,0.000000e+00,
         "process:process_id:0","H1","FindChirpSPtwoPN","LSC-AS_Q",730038491,242431640,2.2665417639062635e+01,730038491,242431640,1.2134316444396973e+01,1.2207031250000000e-03,0.000000e+00,2.646782e-02,-2.098943e+00,6.367139e-01,3.925918e-01,4.327354e-01,2.359374e-01,1.213045e+01,6.309068e-01,3.884639e-01,2.039525e-02,0.000000e+00,1.239329e+01,0.000000e+00,0.000000e+00,0.000000e+00,9.392377e+01,1.123032e+02,15,6.1799859309020864e+00,0.000000e+00,
         "process:process_id:0","H1","FindChirpSPtwoPN","LSC-AS_Q",730044412,961914062,3.1484338667243716e-01,730044412,961914062,9.5477180480957031e+00,9.7656250000000000e-04,0.000000e+00,1.624007e-02,-1.330746e+00,5.735852e-01,5.735851e-01,4.993349e-01,2.500000e-01,9.555675e+00,5.414661e-01,3.410503e-01,1.899623e-02,0.000000e+00,9.775086e+00,0.000000e+00,0.000000e+00,0.000000e+00,1.647405e+02,1.016291e+03,15,7.1577532240696486e+00,0.000000e+00,
         "process:process_id:0","H1","FindChirpSPtwoPN","LSC-AS_Q",730095592,32470703,1.4570175096901755e+01,730095592,32470703,6.3990788459777832e+00,1.2207031250000000e-03,0.000000e+00,6.289946e-02,3.710555e-01,7.268387e-01,7.268387e-01,6.327499e-01,2.500000e-01,6.439632e+00,4.272983e-01,2.912449e-01,1.755446e-02,0.000000e+00,6.593240e+00,0.000000e+00,0.000000e+00,0.000000e+00,4.554374e+01,5.322284e+01,15,8.2063682476016204e+00,0.000000e+00,
         "process:process_id:0","H1","FindChirpSPtwoPN","LSC-AS_Q",730102082,736572265,1.6378084841817618e+01,730102082,736572265,8.7386112213134766e+00,1.2207031250000000e-03,0.000000e+00,2.269854e-02,2.596316e+00,6.045049e-01,6.045049e-01,5.262521e-01,2.500000e-01,8.755040e+00,5.137707e-01,3.293193e-01,1.866667e-02,0.000000e+00,8.958158e+00,0.000000e+00,0.000000e+00,0.000000e+00,1.008521e+02,1.742171e+02,15,5.2404134092075951e+00,0.000000e+00,
         "process:process_id:0","H1","FindChirpSPtwoPN","LSC-AS_Q",730108306,138671875,1.8111540731444126e+01,730108306,138671875,4.5881791114807129e+00,1.2207031250000000e-03,0.000000e+00,3.493666e-02,2.963789e+00,8.840628e-01,8.840627e-01,7.696213e-01,2.500000e-01,4.646430e+00,3.513064e-01,2.556005e-01,1.644520e-02,0.000000e+00,4.758581e+00,0.000000e+00,0.000000e+00,0.000000e+00,9.029975e+01,1.097267e+02,15,9.9525869801889186e+00,0.000000e+00,
         "process:process_id:0","H1","FindChirpSPtwoPN","LSC-AS_Q",730280559,582763671,1.8090723619945347e+01,730280559,582763671,2.4590095520019531e+01,1.2207031250000000e-03,0.000000e+00,2.236931e-02,-2.319643e+00,4.671593e-01,2.331759e-01,2.839410e-01,2.220940e-01,2.448318e+01,9.719507e-01,5.334614e-01,2.407955e-02,0.000000e+00,2.494574e+01,0.000000e+00,0.000000e+00,0.000000e+00,7.591991e+01,2.054240e+02,15,2.8841423430233046e+00,0.000000e+00,
         "process:process_id:0","H1","FindChirpSPtwoPN","LSC-AS_Q",730293268,204101562,2.1630561510134076e+01,730293268,204101562,2.0054519653320312e+01,9.7656250000000000e-04,0.000000e+00,1.010720e-01,1.289040e+00,7.124881e-01,2.039503e-01,3.198605e-01,1.730196e-01,2.007460e+01,9.078348e-01,5.723734e-01,2.603692e-02,0.000000e+00,2.043610e+01,0.000000e+00,0.000000e+00,0.000000e+00,1.848370e+01,5.342556e+01,15,3.4901163012946412e+00,0.000000e+00,
         "process:process_id:0","H1","FindChirpSPtwoPN","LSC-AS_Q",730439496,91308593,1.4360629826432302e+01,730439496,91308593,5.4753108978271484e+01,9.7656250000000000e-04,0.000000e+00,6.053225e-02,-3.030156e+00,2.021784e-01,2.021784e-01,1.760065e-01,2.500000e-01,5.432919e+01,1.536153e+00,6.834822e-01,2.689192e-02,0.000000e+00,5.520876e+01,0.000000e+00,0.000000e+00,0.000000e+00,2.331826e+01,1.436783e+02,15,1.9923518537869473e+00,0.000000e+00,
         "process:process_id:0","H1","FindChirpSPtwoPN","LSC-AS_Q",730471588,454101562,2.3299582255077031e+01,730471588,454101562,1.3788153648376465e+01,1.4648437500000000e-03,0.000000e+00,1.080936e-01,-2.768006e+00,4.610445e-01,4.610444e-01,4.013625e-01,2.500000e-01,1.375160e+01,6.736377e-01,3.945075e-01,2.043082e-02,0.000000e+00,1.405116e+01,0.000000e+00,0.000000e+00,0.000000e+00,2.472635e+01,4.389158e+01,15,7.1436497713979730e+00,0.000000e+00,
         "process:process_id:0","H1","FindChirpSPtwoPN","LSC-AS_Q",730522179,813476562,1.3391213905600210e+01,730522179,813476562,1.3865332603454590e+01,9.7656250000000000e-04,0.000000e+00,3.032953e-02,9.380742e-01,4.595151e-01,4.595150e-01,4.000311e-01,2.500000e-01,1.382796e+01,6.758798e-01,3.953823e-01,2.045346e-02,0.000000e+00,1.412892e+01,0.000000e+00,0.000000e+00,0.000000e+00,8.030141e+01,1.544537e+02,15,5.9316805119639131e+00,0.000000e+00,
         "process:process_id:0","H1","FindChirpSPtwoPN","LSC-AS_Q",730554388,840087890,2.2362661688791380e+01,730554388,840087890,1.1198369979858398e+01,1.4648437500000000e-03,0.000000e+00,6.217625e-02,-2.211379e-01,8.107824e-01,3.460822e-01,4.530996e-01,2.096614e-01,1.123548e+01,6.157328e-01,4.043929e-01,2.113844e-02,0.000000e+00,1.146796e+01,0.000000e+00,0.000000e+00,0.000000e+00,4.400861e+01,3.612993e+01,15,7.4872843670285896e+00,0.000000e+00,
         "process:process_id:0","H1","FindChirpSPtwoPN","LSC-AS_Q",730611443,864501953,1.4254671653190421e+01,730611443,864501953,1.8970201492309570e+01,1.2207031250000000e-03,0.000000e+00,1.292004e-01,-3.049353e+00,7.607210e-01,2.052785e-01,3.304805e-01,1.673459e-01,1.901099e+01,8.852878e-01,5.713612e-01,2.619886e-02,0.000000e+00,1.935111e+01,0.000000e+00,0.000000e+00,0.000000e+00,1.500510e+01,3.542112e+01,15,3.7584210389057033e+00,0.000000e+00,
         "process:process_id:0","H1","FindChirpSPtwoPN","LSC-AS_Q",730617685,902099609,1.5993318244972162e+01,730617685,902099609,7.5994377136230469e+00,9.7656250000000000e-04,0.000000e+00,3.915987e-02,6.951056e-01,6.566263e-01,6.566263e-01,5.716264e-01,2.500000e-01,7.627708e+00,4.729889e-01,3.116532e-01,1.815909e-02,0.000000e+00,7.807203e+00,0.000000e+00,0.000000e+00,0.000000e+00,8.439056e+01,1.211191e+02,15,1.0921194574141648e+01,0.000000e+00,
         "process:process_id:0","H1","FindChirpSPtwoPN","LSC-AS_Q",730624430,157470703,1.7871851720478798e+01,730624430,157470703,1.7664110183715820e+01,1.4648437500000000e-03,0.000000e+00,7.768142e-02,3.070449e+00,7.359365e-01,2.278686e-01,3.450778e-01,1.805287e-01,1.768966e+01,8.336710e-01,5.304421e-01,2.485062e-02,0.000000e+00,1.801774e+01,0.000000e+00,0.000000e+00,0.000000e+00,2.612551e+01,4.336221e+01,15,4.1187358208223470e+00,0.000000e+00,
         "process:process_id:0","H1","FindChirpSPtwoPN","LSC-AS_Q",730630941,76171875,1.9685391999065047e+01,730630941,76171875,1.2513893127441406e+01,9.7656250000000000e-04,0.000000e+00,2.329412e-02,3.027021e+00,4.884308e-01,4.884308e-01,4.252037e-01,2.500000e-01,1.249068e+01,6.358668e-01,3.796194e-01,2.004160e-02,0.000000e+00,1.276697e+01,0.000000e+00,0.000000e+00,0.000000e+00,1.098037e+02,7.995621e+01,15,6.5422435208076068e+00,0.000000e+00,
         "process:process_id:0","H1","FindChirpSPtwoPN","LSC-AS_Q",730694671,909179687,1.3436870410463049e+01,730694671,909179687,8.6131744384765625e+00,1.2207031250000000e-03,0.000000e+00,1.342098e-01,1.700092e+00,6.097062e-01,6.097061e-01,5.307800e-01,2.500000e-01,8.630917e+00,5.093879e-01,3.274437e-01,1.861344e-02,0.000000e+00,8.831473e+00,0.000000e+00,0.000000e+00,0.000000e+00,2.290818e+01,2.242424e+01,15,9.4525611878207219e+00,0.000000e+00,
         "process:process_id:0","H1","FindChirpSPtwoPN","LSC-AS_Q",730796622,70312500,1.7833895804476406e+01,730796622,70312500,9.7980670928955078e+00,1.9531250000000000e-03,0.000000e+00,2.385209e-01,2.219460e+00,5.648443e-01,5.648443e-01,4.917255e-01,2.500000e-01,9.803397e+00,5.498452e-01,3.445598e-01,1.909372e-02,0.000000e+00,1.002778e+01,0.000000e+00,0.000000e+00,0.000000e+00,1.297051e+01,3.256555e+01,15,9.5712112807866081e+00,0.000000e+00,
         "process:process_id:0","H1","FindChirpSPtwoPN","LSC-AS_Q",730802601,12451171,1.9499260244580608e+01,730802601,12451171,6.6815495491027832e+00,9.7656250000000000e-04,0.000000e+00,4.279026e-02,1.375087e+00,7.085370e-01,7.085370e-01,6.168173e-01,2.500000e-01,6.719242e+00,4.383355e-01,2.962389e-01,1.770432e-02,0.000000e+00,6.879043e+00,0.000000e+00,0.000000e+00,0.000000e+00,8.522175e+01,1.440209e+02,15,1.3298137532868150e+01,0.000000e+00,
         "process:process_id:0","H1","FindChirpSPtwoPN","LSC-AS_Q",730866431,397949218,1.3278467820626165e+01,730866431,397949218,2.0065376281738281e+01,2.1972656250000000e-03,0.000000e+00,1.490492e-01,-2.268120e+00,5.476863e-01,2.546442e-01,3.204858e-01,2.166502e-01,2.000936e+01,8.650966e-01,4.994773e-01,2.337964e-02,0.000000e+00,2.039836e+01,0.000000e+00,0.000000e+00,0.000000e+00,1.293864e+01,2.969959e+01,15,3.7190910266303741e+00,0.000000e+00,
         "process:process_id:0","H1","FindChirpSPtwoPN","LSC-AS_Q",730892176,377685546,2.0449430918134748e+01,730892176,377685546,3.8264286041259766e+01,9.7656250000000000e-04,0.000000e+00,1.000213e-01,-6.685733e-01,3.524042e-01,1.818358e-01,2.180143e-01,2.245162e-01,3.802824e+01,1.263359e+00,6.320797e-01,2.617351e-02,0.000000e+00,3.868569e+01,0.000000e+00,0.000000e+00,0.000000e+00,1.342487e+01,4.358440e+01,15,1.8030374717359079e+00,0.000000e+00,
         "process:process_id:0","H1","FindChirpSPtwoPN","LSC-AS_Q",731140485,920410156,1.7613150844499469e+01,731140485,920410156,5.5103249549865723e+00,1.4648437500000000e-03,0.000000e+00,1.032857e-01,3.004440e+00,7.938202e-01,7.938201e-01,6.910606e-01,2.500000e-01,5.559737e+00,3.912434e-01,2.746222e-01,1.704614e-02,0.000000e+00,5.693405e+00,0.000000e+00,0.000000e+00,0.000000e+00,4.311483e+01,6.427241e+01,15,1.9830520960849761e+01,0.000000e+00,
         "process:process_id:0","H1","FindChirpSPtwoPN","LSC-AS_Q",731172240,175048828,2.4579272083648376e+00,731172240,175048828,9.2033290863037109e+00,1.4648437500000000e-03,0.000000e+00,1.672744e-01,-1.125746e+00,5.862198e-01,5.862198e-01,5.103340e-01,2.500000e-01,9.214895e+00,5.297961e-01,3.361322e-01,1.885877e-02,0.000000e+00,9.427418e+00,0.000000e+00,0.000000e+00,0.000000e+00,1.998576e+01,1.595989e+01,15,1.1176347181112179e+01,0.000000e+00,
         "process:process_id:0","H1","FindChirpSPtwoPN","LSC-AS_Q",731185159,812988281,6.0565413048490884e+00,731185159,812988281,5.7268648147583008e+00,1.4648437500000000e-03,0.000000e+00,1.437958e-01,-1.526296e+00,7.760004e-01,7.760003e-01,6.755475e-01,2.500000e-01,5.774148e+00,4.002278e-01,2.788105e-01,1.717564e-02,0.000000e+00,5.912742e+00,0.000000e+00,0.000000e+00,0.000000e+00,2.880158e+01,3.903940e+01,15,1.7152402640672580e+01,0.000000e+00,
         "process:process_id:0","H1","FindChirpSPtwoPN","LSC-AS_Q",731197460,291503906,9.4826957711867159e+00,731197460,291503906,2.9507686614990234e+01,1.4648437500000000e-03,0.000000e+00,8.616621e-02,1.689538e+00,3.436084e-01,2.505952e-01,2.548208e-01,2.438743e-01,2.932175e+01,1.065386e+00,5.420687e-01,2.400685e-02,0.000000e+00,2.986907e+01,0.000000e+00,0.000000e+00,0.000000e+00,2.129804e+01,4.341221e+01,15,3.3678555267335843e+00,0.000000e+00,
         "process:process_id:0","H1","FindChirpSPtwoPN","LSC-AS_Q",731229381,543212890,1.8373987219884164e+01,731229381,543212890,9.3900499343872070e+00,1.2207031250000000e-03,0.000000e+00,3.236616e-01,1.288048e+00,5.792786e-01,5.792786e-01,5.042913e-01,2.500000e-01,9.399657e+00,5.361443e-01,3.388120e-01,1.893379e-02,0.000000e+00,9.615924e+00,0.000000e+00,0.000000e+00,0.000000e+00,1.016384e+01,2.117065e+01,15,1.0821764850245778e+01,0.000000e+00,
         "process:process_id:0","H1","FindChirpSPtwoPN","LSC-AS_Q",731242539,957275390,2.2039109616747332e+01,731242539,957275390,1.6386077880859375e+01,9.7656250000000000e-04,0.000000e+00,9.144577e-02,4.900710e-01,6.375164e-01,2.795520e-01,3.614864e-01,2.119095e-01,1.637173e+01,7.701994e-01,4.671168e-01,2.268232e-02,0.000000e+00,1.669749e+01,0.000000e+00,0.000000e+00,0.000000e+00,2.721321e+01,3.546789e+01,15,6.1927979747149697e+00,0.000000e+00,
         "process:process_id:0","H1","FindChirpSPtwoPN","LSC-AS_Q",731318461,633544921,1.9186204876531331e+01,731318461,633544921,4.9812960624694824e+00,9.7656250000000000e-04,0.000000e+00,4.919246e-01,2.704488e+00,8.423874e-01,8.423873e-01,7.333408e-01,2.500000e-01,5.035834e+00,3.686866e-01,2.639627e-01,1.671204e-02,0.000000e+00,5.157270e+00,0.000000e+00,0.000000e+00,0.000000e+00,8.695457e+00,2.547241e+01,15,1.8297082624727313e+01,0.000000e+00,
         "process:process_id:0","H1","FindChirpSPtwoPN","LSC-AS_Q",731388846,796142578,1.4791168981922997e+01,731388846,796142578,1.7281700134277344e+01,1.2207031250000000e-03,0.000000e+00,1.082590e-01,-1.114637e+00,7.011252e-01,2.430106e-01,3.498208e-01,1.911401e-01,1.729173e+01,8.124548e-01,5.079281e-01,2.405741e-02,0.000000e+00,1.762032e+01,0.000000e+00,0.000000e+00,0.000000e+00,2.094756e+01,2.828531e+01,15,5.1427485828277559e+00,0.000000e+00,
         "process:process_id:0","H1","FindChirpSPtwoPN","LSC-AS_Q",731739274,332275390,1.6398662033441166e+01,731739274,332275390,3.5188323974609375e+01,9.7656250000000000e-04,0.000000e+00,1.356708e-01,1.844234e+00,2.634892e-01,2.634892e-01,2.293807e-01,2.500000e-01,3.493975e+01,1.178708e+00,5.728512e-01,2.461950e-02,0.000000e+00,3.557023e+01,0.000000e+00,0.000000e+00,0.000000e+00,1.128930e+01,3.123762e+01,15,2.3458865354881819e+00,0.000000e+00,
         "process:process_id:0","H1","FindChirpSPtwoPN","LSC-AS_Q",732000162,903320312,1.7066123229265212e+01,732000162,903320312,1.0787827491760254e+01,1.4648437500000000e-03,0.000000e+00,5.960238e-02,2.254980e+00,7.937838e-01,3.675263e-01,4.634520e-01,2.163188e-01,1.082032e+01,5.984027e-01,3.909465e-01,2.068869e-02,0.000000e+00,1.104846e+01,0.000000e+00,0.000000e+00,0.000000e+00,5.193728e+01,1.363800e+02,15,9.5826485199893021e+00,0.000000e+00,
         "process:process_id:0","H1","FindChirpSPtwoPN","LSC-AS_Q",732185095,371093750,2.0576899923901593e+01,732185095,371093750,1.0233601570129395e+01,9.7656250000000000e-04,0.000000e+00,4.491991e-02,8.706031e-01,5.504507e-01,5.504507e-01,4.791952e-01,2.500000e-01,1.023435e+01,5.642229e-01,3.505404e-01,1.925872e-02,0.000000e+00,1.046729e+01,0.000000e+00,0.000000e+00,0.000000e+00,7.102528e+01,6.396852e+01,15,1.0178964797059910e+01,0.000000e+00,
         "process:process_id:0","H1","FindChirpSPtwoPN","LSC-AS_Q",732261635,500488281,1.7896258073051772e+01,732261635,500488281,6.7074818611145020e+00,1.4648437500000000e-03,0.000000e+00,1.248845e-01,-2.748329e+00,1.095536e+00,4.691101e-01,6.132783e-01,2.099275e-01,6.783989e+00,4.548016e-01,3.302406e-01,1.909866e-02,0.000000e+00,6.927649e+00,0.000000e+00,0.000000e+00,0.000000e+00,3.279708e+01,4.382148e+01,15,1.6775968868335621e+01,0.000000e+00,
         "process:process_id:0","H1","FindChirpSPtwoPN","LSC-AS_Q",732287093,607177734,9.8731602908422544e-01,732287093,607177734,2.0731582641601562e+01,1.9531250000000000e-03,0.000000e+00,1.330529e-01,-2.187227e+00,6.088293e-01,2.242019e-01,3.140137e-01,1.967036e-01,2.070142e+01,8.997731e-01,5.365258e-01,2.460096e-02,0.000000e+00,2.108927e+01,0.000000e+00,0.000000e+00,0.000000e+00,1.715402e+01,3.025565e+01,15,5.2093197286226527e+00,0.000000e+00,
         "process:process_id:0","H1","FindChirpSPtwoPN","LSC-AS_Q",732293043,246582031,2.6445185397648148e+00,732293043,246582031,5.8892664909362793e+00,9.7656250000000000e-04,0.000000e+00,3.603970e-02,2.213418e+00,8.643808e-01,6.756842e-01,6.642958e-01,2.462469e-01,5.938070e+00,4.080190e-01,2.845205e-01,1.737576e-02,0.000000e+00,6.078945e+00,0.000000e+00,0.000000e+00,0.000000e+00,1.160866e+02,2.272887e+02,15,1.7503574287089272e+01,0.000000e+00,
         "process:process_id:0","H1","FindChirpSPtwoPN","LSC-AS_Q",732305739,178955078,6.1808220439735386e+00,732305739,178955078,3.5228813171386719e+01,1.2207031250000000e-03,0.000000e+00,1.427702e-01,2.776263e+00,3.446004e-01,2.037795e-01,2.291234e-01,2.335141e-01,3.500516e+01,1.193709e+00,5.972317e-01,2.531868e-02,0.000000e+00,3.562696e+01,0.000000e+00,0.000000e+00,0.000000e+00,1.160348e+01,4.025536e+01,15,2.7444293722995483e+00,0.000000e+00,
         "process:process_id:0","H1","FindChirpSPtwoPN","LSC-AS_Q",732344364,802734375,1.6939537950224345e+01,732344364,802734375,2.1598943710327148e+01,4.8828125000000000e-04,0.000000e+00,2.720071e-01,-2.618678e-01,3.527829e-01,3.527829e-01,3.071153e-01,2.500000e-01,2.148219e+01,8.803628e-01,4.715692e-01,2.233731e-02,0.000000e+00,2.191333e+01,0.000000e+00,0.000000e+00,0.000000e+00,7.532498e+00,2.424512e+01,15,4.1979632191627880e+00,0.000000e+00,
         "process:process_id:0","H1","FindChirpSPtwoPN","LSC-AS_Q",732357018,275878906,2.0464014964683187e+01,732357018,275878906,1.2541434288024902e+01,1.4648437500000000e-03,0.000000e+00,1.907200e-01,-2.140901e+00,4.877925e-01,4.877925e-01,4.246480e-01,2.500000e-01,1.251793e+01,6.366988e-01,3.799505e-01,2.005034e-02,0.000000e+00,1.279473e+01,0.000000e+00,0.000000e+00,0.000000e+00,1.475904e+01,3.921490e+01,15,7.9233467286010315e+00,0.000000e+00,
         "process:process_id:0","H1","FindChirpSPtwoPN","LSC-AS_Q",732376103,36865234,1.7798519876143999e+00,732376103,36865234,1.0072792053222656e+01,1.2207031250000000e-03,0.000000e+00,9.654180e-02,-1.772085e+00,8.164342e-01,3.870160e-01,4.827302e-01,2.181694e-01,1.010975e+01,5.735891e-01,3.785278e-01,2.033304e-02,0.000000e+00,1.032514e+01,0.000000e+00,0.000000e+00,0.000000e+00,3.229896e+01,2.915290e+01,15,9.7231692101313918e+00,0.000000e+00,
         "process:process_id:0","H1","FindChirpSPtwoPN","LSC-AS_Q",732388552,946289062,5.2476286933819454e+00,732388552,946289062,3.8975694179534912e+00,1.9531250000000000e-03,0.000000e+00,4.072926e-01,-2.763505e+00,9.727517e-01,9.727517e-01,8.468295e-01,2.500000e-01,3.962061e+00,3.192767e-01,2.398183e-01,1.592940e-02,0.000000e+00,4.057449e+00,0.000000e+00,0.000000e+00,0.000000e+00,1.192938e+01,3.257534e+01,15,2.3607411320004235e+01,0.000000e+00,
         "process:process_id:0","H1","FindChirpSPtwoPN","LSC-AS_Q",732427068,933105468,1.5975806499798265e+01,732427068,933105468,8.1456298828125000e+00,1.2207031250000000e-03,0.000000e+00,6.236677e-02,1.914505e+00,6.301989e-01,6.301988e-01,5.486200e-01,2.500000e-01,8.168240e+00,4.928237e-01,3.203062e-01,1.840946e-02,0.000000e+00,8.359167e+00,0.000000e+00,0.000000e+00,0.000000e+00,6.200064e+01,7.804396e+01,15,1.4951983346445381e+01,0.000000e+00,
         "process:process_id:0","H1","FindChirpSPtwoPN","LSC-AS_Q",732446208,601074218,2.1306937226880756e+01,732446208,601074218,5.6084856986999512e+00,9.7656250000000000e-04,0.000000e+00,1.089267e-01,2.638006e+00,7.856081e-01,7.856080e-01,6.839115e-01,2.500000e-01,5.656937e+00,3.953332e-01,2.765327e-01,1.710533e-02,0.000000e+00,5.792842e+00,0.000000e+00,0.000000e+00,0.000000e+00,4.282963e+01,4.913284e+01,15,2.1764948550333720e+01,0.000000e+00,
         "process:process_id:0","H1","FindChirpSPtwoPN","LSC-AS_Q",732471402,428466796,4.3243832920740051e+00,732471402,428466796,7.5150423049926758e+00,1.2207031250000000e-03,0.000000e+00,1.878831e-02,-1.613285e+00,6.609782e-01,6.609782e-01,5.754150e-01,2.500000e-01,7.544190e+00,4.698747e-01,3.102837e-01,1.811915e-02,0.000000e+00,7.721900e+00,0.000000e+00,0.000000e+00,0.000000e+00,2.084661e+02,5.906124e+02,15,1.5340730410981218e+01,0.000000e+00,
         "process:process_id:0","H1","FindChirpSPtwoPN","LSC-AS_Q",732490712,188232421,9.7028911056203970e+00,732490712,188232421,9.2363967895507812e+00,1.4648437500000000e-03,0.000000e+00,4.006403e-02,-2.283766e-01,8.285639e-01,4.208925e-01,5.083398e-01,2.233855e-01,9.275222e+00,5.423219e-01,3.605576e-01,1.978109e-02,0.000000e+00,9.476768e+00,0.000000e+00,0.000000e+00,0.000000e+00,8.782083e+01,1.352431e+02,15,1.2379538401476806e+01,0.000000e+00,
         "process:process_id:0","H1","FindChirpSPtwoPN","LSC-AS_Q",732516215,882324218,1.6806646910429830e+01,732516215,882324218,1.2131359100341797e+01,1.4648437500000000e-03,0.000000e+00,6.286302e-02,2.899698e+00,4.975327e-01,4.975327e-01,4.331273e-01,2.500000e-01,1.211217e+01,6.242342e-01,3.749753e-01,1.991864e-02,0.000000e+00,1.238134e+01,0.000000e+00,0.000000e+00,0.000000e+00,4.951433e+01,7.688534e+01,15,9.6884046650616966e+00,0.000000e+00,
         "process:process_id:0","H1","FindChirpSPtwoPN","LSC-AS_Q",732522538,935791015,1.8567859521417155e+01,732522538,935791015,1.2014847755432129e+01,1.2207031250000000e-03,0.000000e+00,9.432460e-02,-1.257974e+00,7.429153e-01,3.455012e-01,4.347847e-01,2.166699e-01,1.203531e+01,6.376637e-01,4.075508e-01,2.111860e-02,0.000000e+00,1.228654e+01,0.000000e+00,0.000000e+00,0.000000e+00,3.206001e+01,2.679204e+01,15,9.1448635054969873e+00,0.000000e+00,
         "process:process_id:0","H1","FindChirpSPtwoPN","LSC-AS_Q",732535252,857177734,2.2109173684645857e+01,732535252,857177734,4.9213118553161621e+00,1.2207031250000000e-03,0.000000e+00,4.786148e-02,8.857579e-01,8.484071e-01,8.484071e-01,7.385813e-01,2.500000e-01,4.976423e+00,3.660706e-01,2.627126e-01,1.667242e-02,0.000000e+00,5.096454e+00,0.000000e+00,0.000000e+00,0.000000e+00,9.699306e+01,2.402400e+02,15,2.1550314528107425e+01,0.000000e+00,
         "process:process_id:0","H1","FindChirpSPtwoPN","LSC-AS_Q",732592716,896728515,1.4115110029151870e+01,732592716,896728515,1.9582580566406250e+01,1.7089843750000000e-03,0.000000e+00,6.765654e-02,-5.568199e-01,6.476700e-01,2.265467e-01,3.247754e-01,1.919877e-01,1.957083e+01,8.743046e-01,5.323015e-01,2.460831e-02,0.000000e+00,1.993744e+01,0.000000e+00,0.000000e+00,0.000000e+00,3.989861e+01,6.224834e+01,15,7.2867689447487027e+00,0.000000e+00,
         "process:process_id:0","H1","FindChirpSPtwoPN","LSC-AS_Q",732611776,751708984,1.9424009788052903e+01,732611776,751708984,1.3140880584716797e+01,1.7089843750000000e-03,0.000000e+00,6.388709e-02,-2.546772e+00,8.007528e-01,2.932169e-01,4.117290e-01,1.961900e-01,1.317939e+01,6.865962e-01,4.485697e-01,2.250438e-02,0.000000e+00,1.343992e+01,0.000000e+00,0.000000e+00,0.000000e+00,5.173336e+01,1.516737e+02,15,1.0923647241340598e+01,0.000000e+00,
         "process:process_id:0","H1","FindChirpSPtwoPN","LSC-AS_Q",732694401,748779296,1.8438236691541970e+01,732694401,748779296,9.3100166320800781e+00,9.7656250000000000e-04,0.000000e+00,1.082740e-01,-1.689247e+00,5.822268e-01,5.822268e-01,5.068578e-01,2.500000e-01,9.320464e+00,5.334295e-01,3.376673e-01,1.890178e-02,0.000000e+00,9.535129e+00,0.000000e+00,0.000000e+00,0.000000e+00,3.303078e+01,5.877182e+01,15,1.2790461381467868e+01,0.000000e+00,
         "process:process_id:0","H1","FindChirpSPtwoPN","LSC-AS_Q",732771341,74462890,1.5868786304344734e+01,732771341,74462890,5.4762420654296875e+01,1.7089843750000000e-03,0.000000e+00,8.788028e-02,-1.771597e+00,2.021578e-01,2.021578e-01,1.759886e-01,2.500000e-01,5.433840e+01,1.536309e+00,6.835286e-01,2.689284e-02,0.000000e+00,5.521807e+01,0.000000e+00,0.000000e+00,0.000000e+00,1.608157e+01,2.006171e+01,15,1.9972832551502422e+00,0.000000e+00,
         "process:process_id:0","H1","FindChirpSPtwoPN","LSC-AS_Q",732777167,58593750,1.7491546067467166e+01,732777167,58593750,9.7058229446411133e+00,1.2207031250000000e-03,0.000000e+00,2.874913e-02,-2.175899e+00,5.680234e-01,5.680234e-01,4.944931e-01,2.500000e-01,9.712123e+00,5.467679e-01,3.432730e-01,1.905803e-02,0.000000e+00,9.934676e+00,0.000000e+00,0.000000e+00,0.000000e+00,1.191034e+02,1.247157e+02,15,1.1724585393819268e+01,0.000000e+00,
         "process:process_id:0","H1","FindChirpSPtwoPN","LSC-AS_Q",732783775,670166015,1.9332297547691397e+01,732783775,670166015,3.8423656463623047e+01,1.9531250000000000e-03,0.000000e+00,1.087069e-01,8.392221e-01,2.499724e-01,2.499724e-01,2.176136e-01,2.500000e-01,3.814502e+01,1.242445e+00,5.933201e-01,2.505548e-02,0.000000e+00,3.881920e+01,0.000000e+00,0.000000e+00,0.000000e+00,1.567708e+01,4.882267e+01,15,2.9043185276978503e+00,0.000000e+00,
         "process:process_id:0","H1","FindChirpSPtwoPN","LSC-AS_Q",732866719,110595703,1.8435223118704226e+01,732866719,110595703,8.0364189147949219e+00,1.4648437500000000e-03,0.000000e+00,2.840433e-02,-1.730191e+00,7.800084e-01,5.208474e-01,5.526371e-01,2.400775e-01,8.069522e+00,4.925509e-01,3.265925e-01,1.866481e-02,0.000000e+00,8.254145e+00,0.000000e+00,0.000000e+00,0.000000e+00,1.431983e+02,1.393102e+02,15,1.6544151234790291e+01,0.000000e+00,
         "process:process_id:0","H1","FindChirpSPtwoPN","LSC-AS_Q",733032458,310546875,1.6599939469099045e+01,733032458,310546875,1.9707433700561523e+01,1.4648437500000000e-03,0.000000e+00,2.734582e-01,2.236906e-01,3.726238e-01,3.726238e-01,3.243878e-01,2.500000e-01,1.960982e+01,8.334866e-01,4.546774e-01,2.193360e-02,0.000000e+00,2.001056e+01,0.000000e+00,0.000000e+00,0.000000e+00,1.021037e+01,3.266991e+01,15,7.7958704270422166e+00,0.000000e+00,
         "process:process_id:0","H1","FindChirpSPtwoPN","LSC-AS_Q",733057696,56152343,2.3629618437865542e+01,733057696,56152343,1.0310500144958496e+01,1.2207031250000000e-03,0.000000e+00,2.417723e-02,-1.548897e+00,8.170391e-01,3.768260e-01,4.760353e-01,2.160096e-01,1.034783e+01,5.827416e-01,3.843561e-01,2.051774e-02,0.000000e+00,1.056673e+01,0.000000e+00,0.000000e+00,0.000000e+00,1.493627e+02,1.065562e+03,15,1.3040597381490734e+01,0.000000e+00,
         "process:process_id:0","H1","FindChirpSPtwoPN","LSC-AS_Q",733115110,498535156,1.5621740074435042e+01,733115110,498535156,3.7829307556152344e+01,1.2207031250000000e-03,0.000000e+00,1.557824e-02,-1.577355e+00,3.490796e-01,1.857604e-01,2.195239e-01,2.266887e-01,3.759339e+01,1.252487e+00,6.255538e-01,2.600587e-02,0.000000e+00,3.824633e+01,0.000000e+00,0.000000e+00,0.000000e+00,1.222940e+02,2.695360e+03,15,3.6295063788133968e+00,0.000000e+00,
         "process:process_id:0","H1","FindChirpSPtwoPN","LSC-AS_Q",733127587,657470703,1.9097106821081706e+01,733127587,657470703,5.6382026672363281e+00,1.4648437500000000e-03,0.000000e+00,2.108640e-01,2.744036e+00,7.831666e-01,7.831665e-01,6.817861e-01,2.500000e-01,5.686359e+00,3.965656e-01,2.771071e-01,1.712309e-02,0.000000e+00,5.822940e+00,0.000000e+00,0.000000e+00,0.000000e+00,2.361160e+01,2.470832e+01,15,2.4788817507727114e+01,0.000000e+00,
         "process:process_id:0","H1","FindChirpSPtwoPN","LSC-AS_Q",733210840,917724609,1.8286329087379077e+01,733210840,917724609,9.8052759170532227e+00,1.4648437500000000e-03,0.000000e+00,1.258183e-01,1.465911e+00,9.296591e-01,3.559870e-01,4.898131e-01,2.002235e-01,9.867272e+00,5.747709e-01,3.946824e-01,2.103679e-02,0.000000e+00,1.006840e+01,0.000000e+00,0.000000e+00,0.000000e+00,3.022298e+01,6.646731e+01,15,1.4459796214724106e+01,0.000000e+00,
         "process:process_id:0","H1","FindChirpSPtwoPN","LSC-AS_Q",733217213,285888671,2.0061277714475160e+01,733217213,285888671,1.9100608825683594e+01,9.7656250000000000e-04,0.000000e+00,7.096455e-02,1.229443e+00,8.308058e-01,1.897837e-01,3.287644e-01,1.513757e-01,1.917667e+01,9.111088e-01,6.089105e-01,2.767643e-02,0.000000e+00,1.950654e+01,0.000000e+00,0.000000e+00,0.000000e+00,3.688338e+01,2.094924e+02,15,6.8508490063146334e+00,0.000000e+00,
         "process:process_id:0","H1","FindChirpSPtwoPN","LSC-AS_Q",733299692,202148437,1.9034815518831213e+01,733299692,202148437,5.1738250732421875e+01,1.9531250000000000e-03,0.000000e+00,1.210615e-01,-2.826679e+00,2.091602e-01,2.091602e-01,1.820846e-01,2.500000e-01,5.134040e+01,1.484876e+00,6.681864e-01,2.658931e-02,0.000000e+00,5.218368e+01,0.000000e+00,0.000000e+00,0.000000e+00,1.342093e+01,4.603999e+01,15,2.6398379896392346e+00,0.000000e+00,
         "process:process_id:0","H1","FindChirpSPtwoPN","LSC-AS_Q",733306048,680908203,2.0805338363750941e+01,733306048,680908203,3.7407051086425781e+01,1.2207031250000000e-03,0.000000e+00,5.381152e-02,1.796649e+00,3.516774e-01,1.868959e-01,2.210027e-01,2.265972e-01,3.717508e+01,1.244197e+00,6.229109e-01,2.595221e-02,0.000000e+00,3.782231e+01,0.000000e+00,0.000000e+00,0.000000e+00,3.386012e+01,4.850405e+01,15,3.3199179531313074e+00,0.000000e+00,
         "process:process_id:0","H1","FindChirpSPtwoPN","LSC-AS_Q",733382739,54199218,1.8166545190248225e+01,733382739,54199218,1.1779525756835938e+01,1.2207031250000000e-03,0.000000e+00,9.944680e-03,2.498212e+00,6.889119e-01,3.778815e-01,4.402461e-01,2.287487e-01,1.178751e+01,6.235269e-01,3.912295e-01,2.054294e-02,0.000000e+00,1.204035e+01,0.000000e+00,0.000000e+00,0.000000e+00,3.387160e+02,1.599198e+03,15,1.1346267083677466e+01,0.000000e+00,
         "process:process_id:0","H1","FindChirpSPtwoPN","LSC-AS_Q",733389151,803710937,1.9952741582596467e+01,733389151,803710937,1.1502174377441406e+01,1.4648437500000000e-03,0.000000e+00,9.998886e-02,-9.464399e-03,5.135373e-01,5.135373e-01,4.470602e-01,2.500000e-01,1.148959e+01,6.047797e-01,3.671434e-01,1.970952e-02,0.000000e+00,1.174693e+01,0.000000e+00,0.000000e+00,0.000000e+00,3.533959e+01,6.666124e+01,15,1.2486084265046085e+01,0.000000e+00,
         "process:process_id:0","H1","FindChirpSPtwoPN","LSC-AS_Q",733395143,357421875,2.1621618825019233e+01,733395143,357421875,1.2068931579589844e+01,1.4648437500000000e-03,0.000000e+00,1.869457e-02,-2.284990e+00,5.971527e-01,4.193412e-01,4.342810e-01,2.423502e-01,1.205859e+01,6.257889e-01,3.813559e-01,2.014900e-02,0.000000e+00,1.232317e+01,0.000000e+00,0.000000e+00,0.000000e+00,1.775245e+02,1.775503e+03,15,1.1014055234400896e+01,0.000000e+00,
         "process:process_id:0","H1","FindChirpSPtwoPN","LSC-AS_Q",733401777,311523437,2.3469429170679714e+01,733401777,311523437,6.0220804214477539e+00,1.2207031250000000e-03,0.000000e+00,2.166003e-01,-1.761943e+00,7.533469e-01,7.533468e-01,6.558265e-01,2.500000e-01,6.066426e+00,4.122629e-01,2.843722e-01,1.734610e-02,0.000000e+00,6.211663e+00,0.000000e+00,0.000000e+00,0.000000e+00,2.121442e+01,4.806892e+01,15,2.1114495643527395e+01,0.000000e+00,
         "process:process_id:0","H1","FindChirpSPtwoPN","LSC-AS_Q",733458718,405761718,1.5329705226512418e+01,733458718,405761718,1.0944755554199219e+01,1.2207031250000000e-03,0.000000e+00,1.536187e-01,1.747900e+00,8.170779e-01,3.526025e-01,4.593205e-01,2.105787e-01,1.098301e+01,6.068823e-01,3.996850e-01,2.100115e-02,0.000000e+00,1.121121e+01,0.000000e+00,0.000000e+00,0.000000e+00,2.178164e+01,3.716480e+01,15,1.1196170422868033e+01,0.000000e+00,
         "process:process_id:0","H1","FindChirpSPtwoPN","LSC-AS_Q",733471495,775390625,1.8888692137698332e+01,733471495,775390625,5.9464149475097656e+00,9.7656250000000000e-04,0.000000e+00,1.860124e-01,-1.497361e+00,7.589842e-01,7.589841e-01,6.607341e-01,2.500000e-01,5.991515e+00,4.092008e-01,2.829623e-01,1.730305e-02,0.000000e+00,6.135056e+00,0.000000e+00,0.000000e+00,0.000000e+00,2.414766e+01,7.007996e+01,15,2.0175940455723119e+01,0.000000e+00,
         "process:process_id:0","H1","FindChirpSPtwoPN","LSC-AS_Q",733490608,882568359,2.1242467865761783e-01,733490608,882568359,9.0230512619018555e+00,1.4648437500000000e-03,0.000000e+00,6.496742e-02,2.684156e+00,9.602076e-01,3.793690e-01,5.145916e-01,2.029981e-01,9.088176e+00,5.455945e-01,3.787682e-01,2.056180e-02,0.000000e+00,9.275563e+00,0.000000e+00,0.000000e+00,0.000000e+00,5.493356e+01,7.494112e+01,15,1.2736989520851008e+01,0.000000e+00,
         "process:process_id:0","H1","FindChirpSPtwoPN","LSC-AS_Q",733497159,773437500,2.0370987302975521e+00,733497159,773437500,4.0419812202453613e+00,9.7656250000000000e-04,0.000000e+00,3.838234e-02,-1.404733e+00,9.522568e-01,9.522567e-01,8.289877e-01,2.500000e-01,4.105201e+00,3.261483e-01,2.432471e-01,1.604287e-02,0.000000e+00,4.204145e+00,0.000000e+00,0.000000e+00,0.000000e+00,1.333029e+02,3.543630e+02,15,2.6178357833044601e+01,0.000000e+00,
         "process:process_id:0","H1","FindChirpSPtwoPN","LSC-AS_Q",733548427,988037109,1.6317260491537549e+01,733548427,988037109,1.3165751457214355e+01,9.7656250000000000e-04,0.000000e+00,1.290215e-01,9.735643e-01,6.764234e-01,3.388771e-01,4.119434e-01,2.223677e-01,1.316796e+01,6.697868e-01,4.159512e-01,2.125919e-02,0.000000e+00,1.344306e+01,0.000000e+00,0.000000e+00,0.000000e+00,2.511151e+01,5.753194e+01,15,1.0497113889680698e+01,0.000000e+00,
         "process:process_id:0","H1","FindChirpSPtwoPN","LSC-AS_Q",733554578,722412109,1.8030475648331144e+01,733554578,722412109,3.4078674316406250e+01,1.2207031250000000e-03,0.000000e+00,4.838779e-02,-6.139832e-01,3.903936e-01,1.892744e-01,2.336258e-01,2.199054e-01,3.388804e+01,1.183435e+00,6.111600e-01,2.580808e-02,0.000000e+00,3.448612e+01,0.000000e+00,0.000000e+00,0.000000e+00,4.082072e+01,1.759099e+02,15,3.9015109361585223e+00,0.000000e+00,
         "process:process_id:0","H1","FindChirpSPtwoPN","LSC-AS_Q",733573872,547607421,2.3404545072424742e+01,733573872,547607421,1.0583252906799316e+01,1.4648437500000000e-03,0.000000e+00,4.263774e-02,-3.080019e+00,8.845161e-01,3.416269e-01,4.682162e-01,2.009905e-01,1.063744e+01,6.008224e-01,4.057957e-01,2.131740e-02,0.000000e+00,1.085378e+01,0.000000e+00,0.000000e+00,0.000000e+00,8.145064e+01,3.482458e+02,15,1.2060833108629303e+01,0.000000e+00,
         "process:process_id:0","H1","FindChirpSPtwoPN","LSC-AS_Q",733586675,264892578,2.9705922834740743e+00,733586675,264892578,4.6920342445373535e+00,9.7656250000000000e-04,0.000000e+00,2.214163e-01,-1.840047e+00,8.725217e-01,8.725217e-01,7.595742e-01,2.500000e-01,4.749313e+00,3.559532e-01,2.578495e-01,1.651739e-02,0.000000e+00,4.863934e+00,0.000000e+00,0.000000e+00,0.000000e+00,2.379177e+01,4.301598e+01,15,2.7750630136284702e+01,0.000000e+00,
         "process:process_id:0","H1","FindChirpSPtwoPN","LSC-AS_Q",733643584,745117187,1.8822062631833056e+01,733643584,745117187,7.3940792083740234e+00,1.4648437500000000e-03,0.000000e+00,1.363307e-01,-2.112139e+00,6.673524e-01,6.673524e-01,5.809640e-01,2.500000e-01,7.424475e+00,4.653867e-01,3.083048e-01,1.806127e-02,0.000000e+00,7.599618e+00,0.000000e+00,0.000000e+00,0.000000e+00,3.050459e+01,5.578277e+01,15,1.7294875195966792e+01,0.000000e+00,
         "process:process_id:0","H1","FindChirpSPtwoPN","LSC-AS_Q",733656310,859863281,2.2366773094923960e+01,733656310,859863281,5.6827344894409180e+00,1.2207031250000000e-03,0.000000e+00,1.133403e-01,-9.541262e-01,8.738813e-01,6.967924e-01,6.784476e-01,2.468220e-01,5.733071e+00,3.993540e-01,2.801577e-01,1.723809e-02,0.000000e+00,5.869505e+00,0.000000e+00,0.000000e+00,0.000000e+00,4.061728e+01,4.307592e+01,15,2.1192905000573273e+01,0.000000e+00,
         "process:process_id:0","H1","FindChirpSPtwoPN","LSC-AS_Q",733663131,87890625,2.6646788110749586e-01,733663131,87890625,1.4030940055847168e+01,1.4648437500000000e-03,0.000000e+00,1.419834e-01,1.999106e+00,7.622215e-01,2.845553e-01,3.960755e-01,1.979428e-01,1.405890e+01,7.124429e-01,4.578620e-01,2.270171e-02,0.000000e+00,1.433618e+01,0.000000e+00,0.000000e+00,0.000000e+00,2.092228e+01,2.660170e+01,15,8.8245614440568936e+00,0.000000e+00,
         "process:process_id:0","H1","FindChirpSPtwoPN","LSC-AS_Q",733675478,72265625,3.7055760175072483e+00,733675478,72265625,3.7984134674072266e+01,1.2207031250000000e-03,0.000000e+00,3.414547e-02,-1.111025e+00,2.517003e-01,2.517003e-01,2.191179e-01,2.500000e-01,3.770957e+01,1.233915e+00,5.906015e-01,2.499802e-02,0.000000e+00,3.837788e+01,0.000000e+00,0.000000e+00,0.000000e+00,5.055850e+01,7.019931e+01,15,2.9802617306075647e+00,0.000000e+00,
         "process:process_id:0","H1","FindChirpSPtwoPN","LSC-AS_Q",733720153,81787109,1.6149277580653628e+01,733720153,81787109,1.9724294662475586e+01,1.7089843750000000e-03,0.000000e+00,1.035486e-01,-1.050699e+00,7.452203e-01,2.001616e-01,3.229073e-01,1.668979e-01,1.975990e+01,9.066046e-01,5.811943e-01,2.643873e-02,0.000000e+00,2.011175e+01,0.000000e+00,0.000000e+00,0.000000e+00,2.589445e+01,3.649352e+01,15,7.1895482211268256e+00,0.000000e+00,
         "process:process_id:0","H1","FindChirpSPtwoPN","LSC-AS_Q",734153175,174316406,1.6762518620043991e+01,734153175,174316406,4.3947958946228027e+00,9.7656250000000000e-04,0.000000e+00,7.151771e-02,7.505947e-01,9.066837e-01,9.066837e-01,7.893140e-01,2.500000e-01,4.454834e+00,3.425416e-01,2.513313e-01,1.630728e-02,0.000000e+00,4.562351e+00,0.000000e+00,0.000000e+00,0.000000e+00,7.182355e+01,1.721680e+02,15,2.6385234601151858e+01,0.000000e+00,
         "process:process_id:0","H1","FindChirpSPtwoPN","LSC-AS_Q",734159782,784667968,1.8602991227275794e+01,734159782,784667968,9.4656629562377930e+00,1.2207031250000000e-03,0.000000e+00,7.860647e-02,1.823975e+00,9.248162e-01,3.717575e-01,5.002990e-01,2.045129e-01,9.525002e+00,5.603562e-01,3.842303e-01,2.068476e-02,0.000000e+00,9.721813e+00,0.000000e+00,0.000000e+00,0.000000e+00,4.514433e+01,6.167022e+01,15,1.2592818147129277e+01,0.000000e+00,
         "process:process_id:0","H1","FindChirpSPtwoPN","LSC-AS_Q",734185204,269287109,1.6838485505514675e+00,734185204,269287109,6.1056890487670898e+00,1.4648437500000000e-03,0.000000e+00,6.592287e-02,4.632710e-01,7.472461e-01,7.472461e-01,6.505155e-01,2.500000e-01,6.149197e+00,4.156287e-01,2.859179e-01,1.739318e-02,0.000000e+00,6.296301e+00,0.000000e+00,0.000000e+00,0.000000e+00,5.939833e+01,7.412490e+01,15,1.5332776098895293e+01,0.000000e+00,
         "process:process_id:0","H1","FindChirpSPtwoPN","LSC-AS_Q",734217213,771240234,1.0599721064931817e+01,734217213,771240234,1.3003620147705078e+01,1.2207031250000000e-03,0.000000e+00,2.493397e-02,2.857733e+00,7.617821e-01,3.095926e-01,4.145572e-01,2.054653e-01,1.302988e+01,6.756349e-01,4.343211e-01,2.197553e-02,0.000000e+00,1.329317e+01,0.000000e+00,0.000000e+00,0.000000e+00,1.068198e+02,4.388654e+02,15,7.0939224921388924e+00,0.000000e+00,
         "process:process_id:0","H1","FindChirpSPtwoPN","LSC-AS_Q",734242263,854248046,1.7577128801879784e+01,734242263,854248046,5.4664640426635742e+00,1.4648437500000000e-03,0.000000e+00,1.743539e-01,-2.619974e+00,7.975642e-01,7.975642e-01,6.943200e-01,2.500000e-01,5.516307e+00,3.894068e-01,2.737621e-01,1.701943e-02,0.000000e+00,5.648971e+00,0.000000e+00,0.000000e+00,0.000000e+00,2.953465e+01,5.182035e+01,15,2.6517139865430497e+01,0.000000e+00,
         "process:process_id:0","H1","FindChirpSPtwoPN","LSC-AS_Q",734248811,194824218,1.9400813972242176e+01,734248811,194824218,9.0980386734008789e+00,1.2207031250000000e-03,0.000000e+00,3.574799e-02,-2.190285e+00,5.902330e-01,5.902330e-01,5.138277e-01,2.500000e-01,9.110705e+00,5.261937e-01,3.346068e-01,1.881593e-02,0.000000e+00,9.321109e+00,0.000000e+00,0.000000e+00,0.000000e+00,1.100175e+02,6.064058e+02,15,1.5467721468424358e+01,0.000000e+00,
         "process:process_id:0","H1","FindChirpSPtwoPN","LSC-AS_Q",734267901,162353515,7.1810123558673589e-01,734267901,162353515,5.8863110542297363e+00,1.4648437500000000e-03,0.000000e+00,9.492988e-02,-2.627283e+00,9.171287e-01,6.389472e-01,6.642491e-01,2.420102e-01,5.938766e+00,4.092328e-01,2.875122e-01,1.749766e-02,0.000000e+00,6.077984e+00,0.000000e+00,0.000000e+00,0.000000e+00,4.655950e+01,8.469868e+01,15,1.9535407686692484e+01,0.000000e+00,
         "process:process_id:0","H1","FindChirpSPtwoPN","LSC-AS_Q",734274293,970947265,2.4987433094655476e+00,734274293,970947265,1.3438346862792969e+01,1.2207031250000000e-03,0.000000e+00,1.661215e-02,-3.056874e+00,4.681509e-01,4.681509e-01,4.075490e-01,2.500000e-01,1.340545e+01,6.634120e-01,3.905049e-01,2.032692e-02,0.000000e+00,1.369869e+01,0.000000e+00,0.000000e+00,0.000000e+00,1.729768e+02,2.159102e+02,15,8.2570961764392585e+00,0.000000e+00,
         "process:process_id:0","H1","FindChirpSPtwoPN","LSC-AS_Q",734287149,503906250,6.0795017123801838e+00,734287149,503906250,5.4695200920104980e+00,1.2207031250000000e-03,0.000000e+00,4.278917e-02,2.852362e+00,7.973016e-01,7.973015e-01,6.940913e-01,2.500000e-01,5.519336e+00,3.895351e-01,2.738222e-01,1.702129e-02,0.000000e+00,5.652070e+00,0.000000e+00,0.000000e+00,0.000000e+00,1.035014e+02,4.413827e+02,15,1.9613716163706453e+01,0.000000e+00,
         "process:process_id:0","H1","FindChirpSPtwoPN","LSC-AS_Q",734299899,291259765,9.6308059275978142e+00,734299899,291259765,7.1827549934387207e+00,9.7656250000000000e-04,0.000000e+00,3.763794e-02,7.355748e-01,6.788927e-01,6.788927e-01,5.910104e-01,2.500000e-01,7.215326e+00,4.574757e-01,3.048010e-01,1.795835e-02,0.000000e+00,7.385959e+00,0.000000e+00,0.000000e+00,0.000000e+00,1.078228e+02,1.659525e+02,15,1.6469219950640412e+01,0.000000e+00,
         "process:process_id:0","H1","FindChirpSPtwoPN","LSC-AS_Q",734306023,140869140,1.1336532630158795e+01,734306023,140869140,7.2617726325988770e+00,1.4648437500000000e-03,0.000000e+00,7.669236e-02,2.271090e+00,6.745157e-01,6.745157e-01,5.872000e-01,2.500000e-01,7.293529e+00,4.604443e-01,3.061181e-01,1.799711e-02,0.000000e+00,7.465852e+00,0.000000e+00,0.000000e+00,0.000000e+00,5.358195e+01,5.608349e+01,15,1.6886558953571541e+01,0.000000e+00,
         "process:process_id:0","H1","FindChirpSPtwoPN","LSC-AS_Q",734312407,486083984,1.3114817344753279e+01,734312407,486083984,9.6406135559082031e+00,1.2207031250000000e-03,0.000000e+00,2.063917e-02,-1.889596e+00,6.561275e-01,4.973112e-01,4.963305e-01,2.452604e-01,9.652271e+00,5.464622e-01,3.463804e-01,1.917947e-02,0.000000e+00,9.871532e+00,0.000000e+00,0.000000e+00,0.000000e+00,1.719936e+02,2.285497e+02,15,1.2601115039802808e+01,0.000000e+00,
         "process:process_id:0","H1","FindChirpSPtwoPN","LSC-AS_Q",734344312,483398437,2.2001581323775980e+01,734344312,483398437,7.6061406135559082e+00,1.2207031250000000e-03,0.000000e+00,1.651576e-01,-2.010403e+00,6.562838e-01,6.562838e-01,5.713282e-01,2.500000e-01,7.634344e+00,4.732357e-01,3.117616e-01,1.816225e-02,0.000000e+00,7.813980e+00,0.000000e+00,0.000000e+00,0.000000e+00,2.461967e+01,3.431578e+01,15,1.6533382036118422e+01,0.000000e+00
      </Stream>
   </Table>
</LIGO_LW>